Workbook

Sheet Sheet1
A1: 审批编号 | B1: 客户/项目名称 | C1: 交易合同类型 | D1: 内部类型分类 | E1: 全额部分开票类型 | F1: 不含税金额 | G1: 差额开票金额 | H1: 增值税金额 | I1: 开票总额 | J1: 派遣服务费 | K1: 代理服务费 | L1: 承揽服务费 | M1: 培训收入 | N1: 招聘服务费 | O1: 猎头服务费 | P1: 安心雇收入 | Q1: 小时间承揽服务费 | R1: 内部往来开票 | S1: 代付工资 | T1: 代付个税 | U1: 代付社保 | V1: 代付公积金 | W1: 代付商保 | X1: 代付残保金 | Y1: 代付税金 | Z1: 代付经营费用 | AA1: 代付其他 | AB1: 代付其他政府补贴 | AC1: 租赁转租 | AD1: 总计 | AE1: 总计检验 | AF1: 申请与开票差异 | AG1: 应交增值税 | AH1: 应交城建税 | AI1: 应交教育费附加 | AJ1: 应交地方教育费附加 | AK1: 代付增值税 | AL1: 代付附加税 | AM1: 成本增值税 | AN1: 成本城建税 | AO1: 成本教育费附加 | AP1: 成本地方教育费附加 | AQ1: 辅助列1 | AR1: 辅助2
A2: 202512010914000217639 | B2: 凯辉人才服务（上海）有限公司 | C2: 劳务派遣 | D2: 派遣业务 | E2: 专票（5%） | F2: =ROUND(SUMIF([1]开票!$A$2:$A$1750,[1]申请!AQ2,[1]开票!$C$2:$C$1750),2) -> #VALUE! | G2: =ROUND(SUMIF([1]开票!$A$2:$A$1750,[1]申请!AQ2,[1]开票!$D$2:$D$1750),2) -> 33275 | H2: =ROUND(SUMIF([1]开票!$A$2:$A$1750,[1]申请!AQ2,[1]开票!$E$2:$E$1750),2) -> 11.43 | I2: {=SUM(B3F2:H2)} -> #NAME? | K2: 240 | S2: 20210.4 | T2: 189.6 | U2: 8875 | V2: 4000 | AD2: =SUM(J2:AC2) -> 33515 | AE2: =AD2-SUM(J2:AC2) -> 0 | AF2: =AD2-I2 -> #NAME? | AG2: =ROUND(H2,2) -> 11.43 | AH2: =ROUND(AG2*0.07,2) -> 0.8 | AI2: =ROUND(AG2*0.03,2) -> 0.34 | AJ2: =ROUND(AG2*0.02,2) -> 0.23 | AK2: =IF(AR2,Y2/(AR2*1.12)*AR2,0) -> 0 | AL2: =ROUND(Y2-AK2,2) -> 0 | AM2: =ROUND(AG2-AK2,2) -> 11.43 | AN2: =ROUND(AM2*0.07,2) -> 0.8 | AO2: =ROUND(AM2*0.03,2) -> 0.34 | AP2: =ROUND(AH2+AI2+AJ2-AL2-AN2-AO2,2) -> 0.23 | AQ2: ="TJ"&A2 -> TJ202512010914000217639 | AR2: =IF(E2="无全额",0,MID(E2,4,2)*1) -> 0.05
A3: 202512010936000029991 | B3: 广东-新御运营管理（派遣） | C3: 劳务派遣 | D3: 派遣业务 | E3: 专票（6%） | F3: =ROUND(SUMIF([1]开票!$A$2:$A$1750,[1]申请!AQ3,[1]开票!$C$2:$C$1750),2) -> #VALUE! | G3: =ROUND(SUMIF([1]开票!$A$2:$A$1750,[1]申请!AQ3,[1]开票!$D$2:$D$1750),2) -> 0 | H3: =ROUND(SUMIF([1]开票!$A$2:$A$1750,[1]申请!AQ3,[1]开票!$E$2:$E$1750),2) -> 550.13 | I3: =SUM(F3:H3) -> #VALUE! | J3: 115.19 | Y3: 604.73 | AA3: 8999 | AD3: =SUM(J3:AC3) -> 9718.92 | AE3: =AD3-SUM(J3:AC3) -> 0 | AF3: =AD3-I3 -> #VALUE! | AG3: =ROUND(H3,2) -> 550.13 | AH3: =ROUND(AG3*0.07,2) -> 38.51 | AI3: =ROUND(AG3*0.03,2) -> 16.5 | AJ3: =ROUND(AG3*0.02,2) -> 11 | AK3: =IF(AR3,Y3/(AR3*1.12)*AR3,0) -> 539.9375 | AL3: =ROUND(Y3-AK3,2) -> 64.79 | AM3: =ROUND(AG3-AK3,2) -> 10.19 | AN3: =ROUND(AM3*0.07,2) -> 0.71 | AO3: =ROUND(AM3*0.03,2) -> 0.31 | AP3: =ROUND(AH3+AI3+AJ3-AL3-AN3-AO3,2) -> 0.2 | AQ3: ="TJ"&A3 -> TJ202512010936000029991 | AR3: =IF(E3="无全额",0,MID(E3,4,2)*1) -> 0.06
A4: 202512010952000277009 | B4: 中国中金财富证券有限公司东莞分公司 | C4: 劳务承揽 | D4: 承揽业务 | E4: 专票（6%） | F4: =ROUND(SUMIF([1]开票!$A$2:$A$1750,[1]申请!AQ4,[1]开票!$C$2:$C$1750),2) -> 8773.58 | G4: =ROUND(SUMIF([1]开票!$A$2:$A$1750,[1]申请!AQ4,[1]开票!$D$2:$D$1750),2) -> 0 | H4: =ROUND(SUMIF([1]开票!$A$2:$A$1750,[1]申请!AQ4,[1]开票!$E$2:$E$1750),2) -> 526.42 | I4: =SUM(F4:H4) -> 9300 | L4: 9300 | AD4: =SUM(J4:AC4) -> 9300 | AE4: =AD4-SUM(J4:AC4) -> 0 | AF4: =AD4-I4 -> 0 | AG4: =ROUND(H4,2) -> 526.42 | AH4: =ROUND(AG4*0.07,2) -> 36.85 | AI4: =ROUND(AG4*0.03,2) -> 15.79 | AJ4: =ROUND(AG4*0.02,2) -> 10.53 | AK4: =IF(AR4,Y4/(AR4*1.12)*AR4,0) -> 0 | AL4: =ROUND(Y4-AK4,2) -> 0 | AM4: =ROUND(AG4-AK4,2) -> 526.42 | AN4: =ROUND(AM4*0.07,2) -> 36.85 | AO4: =ROUND(AM4*0.03,2) -> 15.79 | AP4: =ROUND(AH4+AI4+AJ4-AL4-AN4-AO4,2) -> 10.53 | AQ4: ="TJ"&A4 -> TJ202512010952000277009 | AR4: =IF(E4="无全额",0,MID(E4,4,2)*1) -> 0.06
A5: 202512011032000412415 | B5: 蚂蚁HRO | C5: 劳务承揽 | D5: 承揽业务 | E5: 专票（6%） | F5: =ROUND(SUMIF([1]开票!$A$2:$A$1750,[1]申请!AQ5,[1]开票!$C$2:$C$1750),2) -> #VALUE! | G5: =ROUND(SUMIF([1]开票!$A$2:$A$1750,[1]申请!AQ5,[1]开票!$D$2:$D$1750),2) -> 0 | H5: =ROUND(SUMIF([1]开票!$A$2:$A$1750,[1]申请!AQ5,[1]开票!$E$2:$E$1750),2) -> 19285.69 | I5: =SUM(F5:H5) -> #VALUE! | J5: 340713.85 | AD5: =SUM(J5:AC5) -> 340713.85 | AE5: =AD5-SUM(J5:AC5) -> 0 | AF5: =AD5-I5 -> #VALUE! | AG5: =ROUND(H5,2) -> 19285.69 | AH5: =ROUND(AG5*0.07,2) -> 1350 | AI5: =ROUND(AG5*0.03,2) -> 578.57 | AJ5: =ROUND(AG5*0.02,2) -> 385.71 | AK5: =IF(AR5,Y5/(AR5*1.12)*AR5,0) -> 0 | AL5: =ROUND(Y5-AK5,2) -> 0 | AM5: =ROUND(AG5-AK5,2) -> 19285.69 | AN5: =ROUND(AM5*0.07,2) -> 1350 | AO5: =ROUND(AM5*0.03,2) -> 578.57 | AP5: =ROUND(AH5+AI5+AJ5-AL5-AN5-AO5,2) -> 385.71 | AQ5: ="TJ"&A5 -> TJ202512011032000412415 | AR5: =IF(E5="无全额",0,MID(E5,4,2)*1) -> 0.06
A6: 202512011045000017836 | B6: 软通动力信息技术（集团）股份有限公司 | C6: 劳务承揽 | D6: 小时间承揽 | E6: 专票（6%） | F6: =ROUND(SUMIF([1]开票!$A$2:$A$1750,[1]申请!AQ6,[1]开票!$C$2:$C$1750),2) -> 59984.15 | G6: =ROUND(SUMIF([1]开票!$A$2:$A$1750,[1]申请!AQ6,[1]开票!$D$2:$D$1750),2) -> 0 | H6: =ROUND(SUMIF([1]开票!$A$2:$A$1750,[1]申请!AQ6,[1]开票!$E$2:$E$1750),2) -> 3599.05 | I6: =SUM(F6:H6) -> 63583.2 | Q6: 4127.46 | W6: 491.96 | Z6: 58963.78 | AD6: =SUM(J6:AC6) -> 63583.2 | AE6: =AD6-SUM(J6:AC6) -> 0 | AF6: =AD6-I6 -> 0 | AG6: =ROUND(H6,2) -> 3599.05 | AH6: =ROUND(AG6*0.07,2) -> 251.93 | AI6: =ROUND(AG6*0.03,2) -> 107.97 | AJ6: =ROUND(AG6*0.02,2) -> 71.98 | AK6: =IF(AR6,Y6/(AR6*1.12)*AR6,0) -> 0 | AL6: =ROUND(Y6-AK6,2) -> 0 | AM6: =ROUND(AG6-AK6,2) -> 3599.05 | AN6: =ROUND(AM6*0.07,2) -> 251.93 | AO6: =ROUND(AM6*0.03,2) -> 107.97 | AP6: =ROUND(AH6+AI6+AJ6-AL6-AN6-AO6,2) -> 71.98 | AQ6: ="TJ"&A6 -> TJ202512011045000017836 | AR6: =IF(E6="无全额",0,MID(E6,4,2)*1) -> 0.06
A7: 202512011144000382060 | B7: 软通动力信息技术（集团）股份有限公司 | C7: 劳务承揽 | D7: 小时间承揽 | E7: 专票（6%） | F7: =ROUND(SUMIF([1]开票!$A$2:$A$1750,[1]申请!AQ7,[1]开票!$C$2:$C$1750),2) -> 2624.53 | G7: =ROUND(SUMIF([1]开票!$A$2:$A$1750,[1]申请!AQ7,[1]开票!$D$2:$D$1750),2) -> 0 | H7: =ROUND(SUMIF([1]开票!$A$2:$A$1750,[1]申请!AQ7,[1]开票!$E$2:$E$1750),2) -> 157.47 | I7: =SUM(F7:H7) -> 2782 | Q7: 182 | Z7: 2600 | AD7: =SUM(J7:AC7) -> 2782 | AE7: =AD7-SUM(J7:AC7) -> 0 | AF7: =AD7-I7 -> 0 | AG7: =ROUND(H7,2) -> 157.47 | AH7: =ROUND(AG7*0.07,2) -> 11.02 | AI7: =ROUND(AG7*0.03,2) -> 4.72 | AJ7: =ROUND(AG7*0.02,2) -> 3.15 | AK7: =IF(AR7,Y7/(AR7*1.12)*AR7,0) -> 0 | AL7: =ROUND(Y7-AK7,2) -> 0 | AM7: =ROUND(AG7-AK7,2) -> 157.47 | AN7: =ROUND(AM7*0.07,2) -> 11.02 | AO7: =ROUND(AM7*0.03,2) -> 4.72 | AP7: =ROUND(AH7+AI7+AJ7-AL7-AN7-AO7,2) -> 3.15 | AQ7: ="TJ"&A7 -> TJ202512011144000382060 | AR7: =IF(E7="无全额",0,MID(E7,4,2)*1) -> 0.06
A8: 202512011145000566762 | B8: 软通动力信息技术（集团）股份有限公司 | C8: 劳务承揽 | D8: 小时间承揽 | E8: 专票（6%） | F8: =ROUND(SUMIF([1]开票!$A$2:$A$1750,[1]申请!AQ8,[1]开票!$C$2:$C$1750),2) -> 3755.09 | G8: =ROUND(SUMIF([1]开票!$A$2:$A$1750,[1]申请!AQ8,[1]开票!$D$2:$D$1750),2) -> 0 | H8: =ROUND(SUMIF([1]开票!$A$2:$A$1750,[1]申请!AQ8,[1]开票!$E$2:$E$1750),2) -> 225.31 | I8: =SUM(F8:H8) -> 3980.4 | Q8: 260.4 | Z8: 3720 | AD8: =SUM(J8:AC8) -> 3980.4 | AE8: =AD8-SUM(J8:AC8) -> 0 | AF8: =AD8-I8 -> 0 | AG8: =ROUND(H8,2) -> 225.31 | AH8: =ROUND(AG8*0.07,2) -> 15.77 | AI8: =ROUND(AG8*0.03,2) -> 6.76 | AJ8: =ROUND(AG8*0.02,2) -> 4.51 | AK8: =IF(AR8,Y8/(AR8*1.12)*AR8,0) -> 0 | AL8: =ROUND(Y8-AK8,2) -> 0 | AM8: =ROUND(AG8-AK8,2) -> 225.31 | AN8: =ROUND(AM8*0.07,2) -> 15.77 | AO8: =ROUND(AM8*0.03,2) -> 6.76 | AP8: =ROUND(AH8+AI8+AJ8-AL8-AN8-AO8,2) -> 4.51 | AQ8: ="TJ"&A8 -> TJ202512011145000566762 | AR8: =IF(E8="无全额",0,MID(E8,4,2)*1) -> 0.06
A9: 202512011203000030494 | B9: 深圳中外运物流有限公司 | C9: 劳务承揽 | D9: 承揽业务 | E9: 电票（6%） | F9: =ROUND(SUMIF([1]开票!$A$2:$A$1750,[1]申请!AQ9,[1]开票!$C$2:$C$1750),2) -> #VALUE! | G9: =ROUND(SUMIF([1]开票!$A$2:$A$1750,[1]申请!AQ9,[1]开票!$D$2:$D$1750),2) -> 0 | H9: =ROUND(SUMIF([1]开票!$A$2:$A$1750,[1]申请!AQ9,[1]开票!$E$2:$E$1750),2) -> 4394.8 | I9: =SUM(F9:H9) -> #VALUE! | L9: 77641.54 | AD9: =SUM(J9:AC9) -> 77641.54 | AE9: =AD9-SUM(J9:AC9) -> 0 | AF9: =AD9-I9 -> #VALUE! | AG9: =ROUND(H9,2) -> 4394.8 | AH9: =ROUND(AG9*0.07,2) -> 307.64 | AI9: =ROUND(AG9*0.03,2) -> 131.84 | AJ9: =ROUND(AG9*0.02,2) -> 87.9 | AK9: =IF(AR9,Y9/(AR9*1.12)*AR9,0) -> 0 | AL9: =ROUND(Y9-AK9,2) -> 0 | AM9: =ROUND(AG9-AK9,2) -> 4394.8 | AN9: =ROUND(AM9*0.07,2) -> 307.64 | AO9: =ROUND(AM9*0.03,2) -> 131.84 | AP9: =ROUND(AH9+AI9+AJ9-AL9-AN9-AO9,2) -> 87.9 | AQ9: ="TJ"&A9 -> TJ202512011203000030494 | AR9: =IF(E9="无全额",0,MID(E9,4,2)*1) -> 0.06
A10: 202512011334000210352 | B10: 周老师(百果园) | C10: 劳务承揽 | D10: 承揽业务 | E10: 专票（6%） | F10: =ROUND(SUMIF([1]开票!$A$2:$A$1750,[1]申请!AQ10,[1]开票!$C$2:$C$1750),2) -> 25153.77 | G10: =ROUND(SUMIF([1]开票!$A$2:$A$1750,[1]申请!AQ10,[1]开票!$D$2:$D$1750),2) -> 0 | H10: =ROUND(SUMIF([1]开票!$A$2:$A$1750,[1]申请!AQ10,[1]开票!$E$2:$E$1750),2) -> 1509.23 | I10: =SUM(F10:H10) -> 26663 | L10: 26663 | AD10: =SUM(J10:AC10) -> 26663 | AE10: =AD10-SUM(J10:AC10) -> 0 | AF10: =AD10-I10 -> 0 | AG10: =ROUND(H10,2) -> 1509.23 | AH10: =ROUND(AG10*0.07,2) -> 105.65 | AI10: =ROUND(AG10*0.03,2) -> 45.28 | AJ10: =ROUND(AG10*0.02,2) -> 30.18 | AK10: =IF(AR10,Y10/(AR10*1.12)*AR10,0) -> 0 | AL10: =ROUND(Y10-AK10,2) -> 0 | AM10: =ROUND(AG10-AK10,2) -> 1509.23 | AN10: =ROUND(AM10*0.07,2) -> 105.65 | AO10: =ROUND(AM10*0.03,2) -> 45.28 | AP10: =ROUND(AH10+AI10+AJ10-AL10-AN10-AO10,2) -> 30.18 | AQ10: ="TJ"&A10 -> TJ202512011334000210352 | AR10: =IF(E10="无全额",0,MID(E10,4,2)*1) -> 0.06
A11: 202512011519000128722 | B11: 深圳市万科物业服务有限公司东莞茶山分公司 | C11: 劳务派遣 | D11: 派遣业务 | E11: 专票（5%） | F11: =ROUND(SUMIF([1]开票!$A$2:$A$1750,[1]申请!AQ11,[1]开票!$C$2:$C$1750),2) -> #VALUE! | G11: =ROUND(SUMIF([1]开票!$A$2:$A$1750,[1]申请!AQ11,[1]开票!$D$2:$D$1750),2) -> 103040.29 | H11: =ROUND(SUMIF([1]开票!$A$2:$A$1750,[1]申请!AQ11,[1]开票!$E$2:$E$1750),2) -> 39.1 | I11: =SUM(F11:H11) -> #VALUE! | J11: 782 | S11: 84594.74 | T11: 264.58 | U11: 17874.97 | W11: 306 | Y11: 39.1 | AD11: =SUM(J11:AC11) -> 103861.39 | AE11: =AD11-SUM(J11:AC11) -> 0 | AF11: =AD11-I11 -> #VALUE! | AG11: =ROUND(H11,2) -> 39.1 | AH11: =ROUND(AG11*0.07,2) -> 2.74 | AI11: =ROUND(AG11*0.03,2) -> 1.17 | AJ11: =ROUND(AG11*0.02,2) -> 0.78 | AK11: =IF(AR11,Y11/(AR11*1.12)*AR11,0) -> 34.910714 | AL11: =ROUND(Y11-AK11,2) -> 4.19 | AM11: =ROUND(AG11-AK11,2) -> 4.19 | AN11: =ROUND(AM11*0.07,2) -> 0.29 | AO11: =ROUND(AM11*0.03,2) -> 0.13 | AP11: =ROUND(AH11+AI11+AJ11-AL11-AN11-AO11,2) -> 0.08 | AQ11: ="TJ"&A11 -> TJ202512011519000128722 | AR11: =IF(E11="无全额",0,MID(E11,4,2)*1) -> 0.05
A12: 202512011524000290727 | B12: 东莞万江金鳌城市资源经营管理有限公司 | C12: 劳务派遣 | D12: 派遣业务 | E12: 专票（5%） | F12: =ROUND(SUMIF([1]开票!$A$2:$A$1750,[1]申请!AQ12,[1]开票!$C$2:$C$1750),2) -> 460 | G12: =ROUND(SUMIF([1]开票!$A$2:$A$1750,[1]申请!AQ12,[1]开票!$D$2:$D$1750),2) -> 62566.95 | H12: =ROUND(SUMIF([1]开票!$A$2:$A$1750,[1]申请!AQ12,[1]开票!$E$2:$E$1750),2) -> 23 | I12: =SUM(F12:H12) -> 63049.95 | J12: 460 | S12: 52661.58 | T12: 90.3 | U12: 9635.07 | W12: 180 | Y12: 23 | AD12: =SUM(J12:AC12) -> 63049.95 | AE12: =AD12-SUM(J12:AC12) -> 0 | AF12: =AD12-I12 -> 0 | AG12: =ROUND(H12,2) -> 23 | AH12: =ROUND(AG12*0.07,2) -> 1.61 | AI12: =ROUND(AG12*0.03,2) -> 0.69 | AJ12: =ROUND(AG12*0.02,2) -> 0.46 | AK12: =IF(AR12,Y12/(AR12*1.12)*AR12,0) -> 20.535714 | AL12: =ROUND(Y12-AK12,2) -> 2.46 | AM12: =ROUND(AG12-AK12,2) -> 2.46 | AN12: =ROUND(AM12*0.07,2) -> 0.17 | AO12: =ROUND(AM12*0.03,2) -> 0.07 | AP12: =ROUND(AH12+AI12+AJ12-AL12-AN12-AO12,2) -> 0.06 | AQ12: ="TJ"&A12 -> TJ202512011524000290727 | AR12: =IF(E12="无全额",0,MID(E12,4,2)*1) -> 0.05
A13: 202512011528000448156 | B13: 东莞万江金鳌城市资源经营管理有限公司 | C13: 劳务派遣 | D13: 派遣业务 | E13: 专票（5%） | F13: =ROUND(SUMIF([1]开票!$A$2:$A$1750,[1]申请!AQ13,[1]开票!$C$2:$C$1750),2) -> 92 | G13: =ROUND(SUMIF([1]开票!$A$2:$A$1750,[1]申请!AQ13,[1]开票!$D$2:$D$1750),2) -> 6459.84 | H13: =ROUND(SUMIF([1]开票!$A$2:$A$1750,[1]申请!AQ13,[1]开票!$E$2:$E$1750),2) -> 4.6 | I13: =SUM(F13:H13) -> 6556.44 | J13: 92 | S13: 6400 | T13: 0 | U13: 23.84 | W13: 36 | Y13: 4.6 | AD13: =SUM(J13:AC13) -> 6556.44 | AE13: =AD13-SUM(J13:AC13) -> 0 | AF13: =AD13-I13 -> 0 | AG13: =ROUND(H13,2) -> 4.6 | AH13: =ROUND(AG13*0.07,2) -> 0.32 | AI13: =ROUND(AG13*0.03,2) -> 0.14 | AJ13: =ROUND(AG13*0.02,2) -> 0.09 | AK13: =IF(AR13,Y13/(AR13*1.12)*AR13,0) -> 4.1071429 | AL13: =ROUND(Y13-AK13,2) -> 0.49 | AM13: =ROUND(AG13-AK13,2) -> 0.49 | AN13: =ROUND(AM13*0.07,2) -> 0.03 | AO13: =ROUND(AM13*0.03,2) -> 0.01 | AP13: =ROUND(AH13+AI13+AJ13-AL13-AN13-AO13,2) -> 0.02 | AQ13: ="TJ"&A13 -> TJ202512011528000448156 | AR13: =IF(E13="无全额",0,MID(E13,4,2)*1) -> 0.05
A14: 202512011754000073051 | B14: 广州市南海中学 | C14: 劳务派遣 | D14: 派遣业务 | E14: 专票（5%） | F14: =ROUND(SUMIF([1]开票!$A$2:$A$1750,[1]申请!AQ14,[1]开票!$C$2:$C$1750),2) -> 2042.85 | G14: =ROUND(SUMIF([1]开票!$A$2:$A$1750,[1]申请!AQ14,[1]开票!$D$2:$D$1750),2) -> 270816.8 | H14: =ROUND(SUMIF([1]开票!$A$2:$A$1750,[1]申请!AQ14,[1]开票!$E$2:$E$1750),2) -> 102.15 | I14: =SUM(F14:H14) -> 272961.8 | J14: 2145 | S14: 183162.12 | T14: 986.61 | U14: 65701.19 | V14: 19470 | W14: 0 | X14: 1496.88 | AD14: =SUM(J14:AC14) -> 272961.8 | AE14: =AD14-SUM(J14:AC14) -> 0 | AF14: =AD14-I14 -> 0 | AG14: =ROUND(H14,2) -> 102.15 | AH14: =ROUND(AG14*0.07,2) -> 7.15 | AI14: =ROUND(AG14*0.03,2) -> 3.06 | AJ14: =ROUND(AG14*0.02,2) -> 2.04 | AK14: =IF(AR14,Y14/(AR14*1.12)*AR14,0) -> 0 | AL14: =ROUND(Y14-AK14,2) -> 0 | AM14: =ROUND(AG14-AK14,2) -> 102.15 | AN14: =ROUND(AM14*0.07,2) -> 7.15 | AO14: =ROUND(AM14*0.03,2) -> 3.06 | AP14: =ROUND(AH14+AI14+AJ14-AL14-AN14-AO14,2) -> 2.04 | AQ14: ="TJ"&A14 -> TJ202512011754000073051 | AR14: =IF(E14="无全额",0,MID(E14,4,2)*1) -> 0.05
A15: 202512020912000234377 | B15: 广州市第一中学 | C15: 劳务派遣 | D15: 派遣业务 | E15: 普票（5%） | F15: =ROUND(SUMIF([1]开票!$A$2:$A$1750,[1]申请!AQ15,[1]开票!$C$2:$C$1750),2) -> 0 | G15: =ROUND(SUMIF([1]开票!$A$2:$A$1750,[1]申请!AQ15,[1]开票!$D$2:$D$1750),2) -> 239913.88 | H15: =ROUND(SUMIF([1]开票!$A$2:$A$1750,[1]申请!AQ15,[1]开票!$E$2:$E$1750),2) -> 0 | I15: =SUM(F15:H15) -> 239913.88 | S15: 239913.88 | AD15: =SUM(J15:AC15) -> 239913.88 | AE15: =AD15-SUM(J15:AC15) -> 0 | AF15: =AD15-I15 -> 0 | AG15: =ROUND(H15,2) -> 0 | AH15: =ROUND(AG15*0.07,2) -> 0 | AI15: =ROUND(AG15*0.03,2) -> 0 | AJ15: =ROUND(AG15*0.02,2) -> 0 | AK15: =IF(AR15,Y15/(AR15*1.12)*AR15,0) -> 0 | AL15: =ROUND(Y15-AK15,2) -> 0 | AM15: =ROUND(AG15-AK15,2) -> 0 | AN15: =ROUND(AM15*0.07,2) -> 0 | AO15: =ROUND(AM15*0.03,2) -> 0 | AP15: =ROUND(AH15+AI15+AJ15-AL15-AN15-AO15,2) -> 0 | AQ15: ="TJ"&A15 -> TJ202512020912000234377 | AR15: =IF(E15="无全额",0,MID(E15,4,2)*1) -> 0.05
A16: 202512020914000230838 | B16: 广州市第一中学 | C16: 劳务派遣 | D16: 派遣业务 | E16: 专票（6%） | F16: =ROUND(SUMIF([1]开票!$A$2:$A$1750,[1]申请!AQ16,[1]开票!$C$2:$C$1750),2) -> 35.85 | G16: =ROUND(SUMIF([1]开票!$A$2:$A$1750,[1]申请!AQ16,[1]开票!$D$2:$D$1750),2) -> 0 | H16: =ROUND(SUMIF([1]开票!$A$2:$A$1750,[1]申请!AQ16,[1]开票!$E$2:$E$1750),2) -> 2.15 | I16: =SUM(F16:H16) -> 38 | P16: 11 | W16: 27 | AD16: =SUM(J16:AC16) -> 38 | AE16: =AD16-SUM(J16:AC16) -> 0 | AF16: =AD16-I16 -> 0 | AG16: =ROUND(H16,2) -> 2.15 | AH16: =ROUND(AG16*0.07,2) -> 0.15 | AI16: =ROUND(AG16*0.03,2) -> 0.06 | AJ16: =ROUND(AG16*0.02,2) -> 0.04 | AK16: =IF(AR16,Y16/(AR16*1.12)*AR16,0) -> 0 | AL16: =ROUND(Y16-AK16,2) -> 0 | AM16: =ROUND(AG16-AK16,2) -> 2.15 | AN16: =ROUND(AM16*0.07,2) -> 0.15 | AO16: =ROUND(AM16*0.03,2) -> 0.06 | AP16: =ROUND(AH16+AI16+AJ16-AL16-AN16-AO16,2) -> 0.04 | AQ16: ="TJ"&A16 -> TJ202512020914000230838 | AR16: =IF(E16="无全额",0,MID(E16,4,2)*1) -> 0.06
A17: 202512020916000393523 | B17: 广州市第一中学 | C17: 劳务派遣 | D17: 派遣业务 | E17: 普票（5%） | F17: =ROUND(SUMIF([1]开票!$A$2:$A$1750,[1]申请!AQ17,[1]开票!$C$2:$C$1750),2) -> 557.14 | G17: =ROUND(SUMIF([1]开票!$A$2:$A$1750,[1]申请!AQ17,[1]开票!$D$2:$D$1750),2) -> 73517.47 | H17: =ROUND(SUMIF([1]开票!$A$2:$A$1750,[1]申请!AQ17,[1]开票!$E$2:$E$1750),2) -> 27.86 | I17: =SUM(F17:H17) -> 74102.47 | K17: 585 | S17: 53655.63 | T17: 741.33 | U17: 14741.63 | V17: 4016 | X17: 362.88 | AD17: =SUM(J17:AC17) -> 74102.47 | AE17: =AD17-SUM(J17:AC17) -> 0 | AF17: =AD17-I17 -> 0 | AG17: =ROUND(H17,2) -> 27.86 | AH17: =ROUND(AG17*0.07,2) -> 1.95 | AI17: =ROUND(AG17*0.03,2) -> 0.84 | AJ17: =ROUND(AG17*0.02,2) -> 0.56 | AK17: =IF(AR17,Y17/(AR17*1.12)*AR17,0) -> 0 | AL17: =ROUND(Y17-AK17,2) -> 0 | AM17: =ROUND(AG17-AK17,2) -> 27.86 | AN17: =ROUND(AM17*0.07,2) -> 1.95 | AO17: =ROUND(AM17*0.03,2) -> 0.84 | AP17: =ROUND(AH17+AI17+AJ17-AL17-AN17-AO17,2) -> 0.56 | AQ17: ="TJ"&A17 -> TJ202512020916000393523 | AR17: =IF(E17="无全额",0,MID(E17,4,2)*1) -> 0.05
A18: 202512020921000119648 | B18: 广州市第一中学 | C18: 劳务派遣 | D18: 派遣业务 | E18: 普票（5%） | F18: =ROUND(SUMIF([1]开票!$A$2:$A$1750,[1]申请!AQ18,[1]开票!$C$2:$C$1750),2) -> 1238.1 | G18: =ROUND(SUMIF([1]开票!$A$2:$A$1750,[1]申请!AQ18,[1]开票!$D$2:$D$1750),2) -> 182425.8 | H18: =ROUND(SUMIF([1]开票!$A$2:$A$1750,[1]申请!AQ18,[1]开票!$E$2:$E$1750),2) -> 61.9 | I18: =SUM(F18:H18) -> 183725.8 | K18: 1300 | S18: 136343.93 | T18: 1558.87 | U18: 36447.8 | V18: 7168 | X18: 907.2 | AD18: =SUM(J18:AC18) -> 183725.8 | AE18: =AD18-SUM(J18:AC18) -> 0 | AF18: =AD18-I18 -> 0 | AG18: =ROUND(H18,2) -> 61.9 | AH18: =ROUND(AG18*0.07,2) -> 4.33 | AI18: =ROUND(AG18*0.03,2) -> 1.86 | AJ18: =ROUND(AG18*0.02,2) -> 1.24 | AK18: =IF(AR18,Y18/(AR18*1.12)*AR18,0) -> 0 | AL18: =ROUND(Y18-AK18,2) -> 0 | AM18: =ROUND(AG18-AK18,2) -> 61.9 | AN18: =ROUND(AM18*0.07,2) -> 4.33 | AO18: =ROUND(AM18*0.03,2) -> 1.86 | AP18: =ROUND(AH18+AI18+AJ18-AL18-AN18-AO18,2) -> 1.24 | AQ18: ="TJ"&A18 -> TJ202512020921000119648 | AR18: =IF(E18="无全额",0,MID(E18,4,2)*1) -> 0.05
A19: 202512020927000032377 | B19: 广州市南海中学 | C19: 劳务派遣 | D19: 派遣业务 | E19: 专票（5%） | F19: =ROUND(SUMIF([1]开票!$A$2:$A$1750,[1]申请!AQ19,[1]开票!$C$2:$C$1750),2) -> 0 | G19: =ROUND(SUMIF([1]开票!$A$2:$A$1750,[1]申请!AQ19,[1]开票!$D$2:$D$1750),2) -> 12772.5 | H19: =ROUND(SUMIF([1]开票!$A$2:$A$1750,[1]申请!AQ19,[1]开票!$E$2:$E$1750),2) -> 0 | I19: =SUM(F19:H19) -> 12772.5 | J19: 0 | S19: 12772.5 | T19: 0 | U19: 0 | V19: 0 | W19: 0 | X19: 0 | AD19: =SUM(J19:AC19) -> 12772.5 | AE19: =AD19-SUM(J19:AC19) -> 0 | AF19: =AD19-I19 -> 0 | AG19: =ROUND(H19,2) -> 0 | AH19: =ROUND(AG19*0.07,2) -> 0 | AI19: =ROUND(AG19*0.03,2) -> 0 | AJ19: =ROUND(AG19*0.02,2) -> 0 | AK19: =IF(AR19,Y19/(AR19*1.12)*AR19,0) -> 0 | AL19: =ROUND(Y19-AK19,2) -> 0 | AM19: =ROUND(AG19-AK19,2) -> 0 | AN19: =ROUND(AM19*0.07,2) -> 0 | AO19: =ROUND(AM19*0.03,2) -> 0 | AP19: =ROUND(AH19+AI19+AJ19-AL19-AN19-AO19,2) -> 0 | AQ19: ="TJ"&A19 -> TJ202512020927000032377 | AR19: =IF(E19="无全额",0,MID(E19,4,2)*1) -> 0.05
A20: 202512021410000083517 | B20: 软通动力信息技术（集团）股份有限公司 | C20: 劳务承揽 | D20: 小时间承揽 | E20: 专票（6%） | F20: =ROUND(SUMIF([1]开票!$A$2:$A$1750,[1]申请!AQ20,[1]开票!$C$2:$C$1750),2) -> 111307.88 | G20: =ROUND(SUMIF([1]开票!$A$2:$A$1750,[1]申请!AQ20,[1]开票!$D$2:$D$1750),2) -> 0 | H20: =ROUND(SUMIF([1]开票!$A$2:$A$1750,[1]申请!AQ20,[1]开票!$E$2:$E$1750),2) -> 6678.47 | I20: =SUM(F20:H20) -> 117986.35 | Q20: 7684.25 | W20: 527.1 | Z20: 109775 | AD20: =SUM(J20:AC20) -> 117986.35 | AE20: =AD20-SUM(J20:AC20) -> 0 | AF20: =AD20-I20 -> 0 | AG20: =ROUND(H20,2) -> 6678.47 | AH20: =ROUND(AG20*0.07,2) -> 467.49 | AI20: =ROUND(AG20*0.03,2) -> 200.35 | AJ20: =ROUND(AG20*0.02,2) -> 133.57 | AK20: =IF(AR20,Y20/(AR20*1.12)*AR20,0) -> 0 | AL20: =ROUND(Y20-AK20,2) -> 0 | AM20: =ROUND(AG20-AK20,2) -> 6678.47 | AN20: =ROUND(AM20*0.07,2) -> 467.49 | AO20: =ROUND(AM20*0.03,2) -> 200.35 | AP20: =ROUND(AH20+AI20+AJ20-AL20-AN20-AO20,2) -> 133.57 | AQ20: ="TJ"&A20 -> TJ202512021410000083517 | AR20: =IF(E20="无全额",0,MID(E20,4,2)*1) -> 0.06
A21: 202512021519000271014 | B21: 广州市南海中学 | C21: 劳务派遣 | D21: 派遣业务 | E21: 专票（5%） | F21: =ROUND(SUMIF([1]开票!$A$2:$A$1750,[1]申请!AQ21,[1]开票!$C$2:$C$1750),2) -> 309.52 | G21: =ROUND(SUMIF([1]开票!$A$2:$A$1750,[1]申请!AQ21,[1]开票!$D$2:$D$1750),2) -> 28528.58 | H21: =ROUND(SUMIF([1]开票!$A$2:$A$1750,[1]申请!AQ21,[1]开票!$E$2:$E$1750),2) -> 15.48 | I21: =SUM(F21:H21) -> 28853.58 | J21: 325 | S21: 24000 | T21: 4528.58 | U21: 0 | V21: 0 | W21: 0 | X21: 0 | AD21: =SUM(J21:AC21) -> 28853.58 | AE21: =AD21-SUM(J21:AC21) -> 0 | AF21: =AD21-I21 -> 0 | AG21: =ROUND(H21,2) -> 15.48 | AH21: =ROUND(AG21*0.07,2) -> 1.08 | AI21: =ROUND(AG21*0.03,2) -> 0.46 | AJ21: =ROUND(AG21*0.02,2) -> 0.31 | AK21: =IF(AR21,Y21/(AR21*1.12)*AR21,0) -> 0 | AL21: =ROUND(Y21-AK21,2) -> 0 | AM21: =ROUND(AG21-AK21,2) -> 15.48 | AN21: =ROUND(AM21*0.07,2) -> 1.08 | AO21: =ROUND(AM21*0.03,2) -> 0.46 | AP21: =ROUND(AH21+AI21+AJ21-AL21-AN21-AO21,2) -> 0.31 | AQ21: ="TJ"&A21 -> TJ202512021519000271014 | AR21: =IF(E21="无全额",0,MID(E21,4,2)*1) -> 0.05
A22: 202512021609000063803 | B22: 软通动力信息技术（集团）股份有限公司 | C22: 劳务承揽 | D22: 小时间承揽 | E22: 专票（6%） | F22: =ROUND(SUMIF([1]开票!$A$2:$A$1750,[1]申请!AQ22,[1]开票!$C$2:$C$1750),2) -> 1312.26 | G22: =ROUND(SUMIF([1]开票!$A$2:$A$1750,[1]申请!AQ22,[1]开票!$D$2:$D$1750),2) -> 0 | H22: =ROUND(SUMIF([1]开票!$A$2:$A$1750,[1]申请!AQ22,[1]开票!$E$2:$E$1750),2) -> 78.74 | I22: =SUM(F22:H22) -> 1391 | Q22: 91 | Z22: 1300 | AD22: =SUM(J22:AC22) -> 1391 | AE22: =AD22-SUM(J22:AC22) -> 0 | AF22: =AD22-I22 -> 0 | AG22: =ROUND(H22,2) -> 78.74 | AH22: =ROUND(AG22*0.07,2) -> 5.51 | AI22: =ROUND(AG22*0.03,2) -> 2.36 | AJ22: =ROUND(AG22*0.02,2) -> 1.57 | AK22: =IF(AR22,Y22/(AR22*1.12)*AR22,0) -> 0 | AL22: =ROUND(Y22-AK22,2) -> 0 | AM22: =ROUND(AG22-AK22,2) -> 78.74 | AN22: =ROUND(AM22*0.07,2) -> 5.51 | AO22: =ROUND(AM22*0.03,2) -> 2.36 | AP22: =ROUND(AH22+AI22+AJ22-AL22-AN22-AO22,2) -> 1.57 | AQ22: ="TJ"&A22 -> TJ202512021609000063803 | AR22: =IF(E22="无全额",0,MID(E22,4,2)*1) -> 0.06
A23: 202512021611000107980 | B23: 软通动力信息技术（集团）股份有限公司 | C23: 劳务承揽 | D23: 小时间承揽 | E23: 专票（6%） | F23: =ROUND(SUMIF([1]开票!$A$2:$A$1750,[1]申请!AQ23,[1]开票!$C$2:$C$1750),2) -> 39632.98 | G23: =ROUND(SUMIF([1]开票!$A$2:$A$1750,[1]申请!AQ23,[1]开票!$D$2:$D$1750),2) -> 0 | H23: =ROUND(SUMIF([1]开票!$A$2:$A$1750,[1]申请!AQ23,[1]开票!$E$2:$E$1750),2) -> 2377.98 | I23: =SUM(F23:H23) -> 42010.96 | Q23: 2748.38 | Z23: 39262.58 | AD23: =SUM(J23:AC23) -> 42010.96 | AE23: =AD23-SUM(J23:AC23) -> 0 | AF23: =AD23-I23 -> 0 | AG23: =ROUND(H23,2) -> 2377.98 | AH23: =ROUND(AG23*0.07,2) -> 166.46 | AI23: =ROUND(AG23*0.03,2) -> 71.34 | AJ23: =ROUND(AG23*0.02,2) -> 47.56 | AK23: =IF(AR23,Y23/(AR23*1.12)*AR23,0) -> 0 | AL23: =ROUND(Y23-AK23,2) -> 0 | AM23: =ROUND(AG23-AK23,2) -> 2377.98 | AN23: =ROUND(AM23*0.07,2) -> 166.46 | AO23: =ROUND(AM23*0.03,2) -> 71.34 | AP23: =ROUND(AH23+AI23+AJ23-AL23-AN23-AO23,2) -> 47.56 | AQ23: ="TJ"&A23 -> TJ202512021611000107980 | AR23: =IF(E23="无全额",0,MID(E23,4,2)*1) -> 0.06
A24: 202512021613000555164 | B24: 软通动力信息技术（集团）股份有限公司 | C24: 劳务承揽 | D24: 小时间承揽 | E24: 专票（6%） | F24: =ROUND(SUMIF([1]开票!$A$2:$A$1750,[1]申请!AQ24,[1]开票!$C$2:$C$1750),2) -> 90166.55 | G24: =ROUND(SUMIF([1]开票!$A$2:$A$1750,[1]申请!AQ24,[1]开票!$D$2:$D$1750),2) -> 0 | H24: =ROUND(SUMIF([1]开票!$A$2:$A$1750,[1]申请!AQ24,[1]开票!$E$2:$E$1750),2) -> 5409.99 | I24: =SUM(F24:H24) -> 95576.54 | Q24: 6192.9 | W24: 913.64 | Z24: 88470 | AD24: =SUM(J24:AC24) -> 95576.54 | AE24: =AD24-SUM(J24:AC24) -> 0 | AF24: =AD24-I24 -> 0 | AG24: =ROUND(H24,2) -> 5409.99 | AH24: =ROUND(AG24*0.07,2) -> 378.7 | AI24: =ROUND(AG24*0.03,2) -> 162.3 | AJ24: =ROUND(AG24*0.02,2) -> 108.2 | AK24: =IF(AR24,Y24/(AR24*1.12)*AR24,0) -> 0 | AL24: =ROUND(Y24-AK24,2) -> 0 | AM24: =ROUND(AG24-AK24,2) -> 5409.99 | AN24: =ROUND(AM24*0.07,2) -> 378.7 | AO24: =ROUND(AM24*0.03,2) -> 162.3 | AP24: =ROUND(AH24+AI24+AJ24-AL24-AN24-AO24,2) -> 108.2 | AQ24: ="TJ"&A24 -> TJ202512021613000555164 | AR24: =IF(E24="无全额",0,MID(E24,4,2)*1) -> 0.06
A25: 202512021636000598013 | B25: 蚂蚁HRO | C25: 劳务承揽 | D25: 承揽业务 | E25: 专票（6%） | F25: =ROUND(SUMIF([1]开票!$A$2:$A$1750,[1]申请!AQ25,[1]开票!$C$2:$C$1750),2) -> 13469.15 | G25: =ROUND(SUMIF([1]开票!$A$2:$A$1750,[1]申请!AQ25,[1]开票!$D$2:$D$1750),2) -> 0 | H25: =ROUND(SUMIF([1]开票!$A$2:$A$1750,[1]申请!AQ25,[1]开票!$E$2:$E$1750),2) -> 808.15 | I25: =SUM(F25:H25) -> 14277.3 | J25: 14277.3 | AD25: =SUM(J25:AC25) -> 14277.3 | AE25: =AD25-SUM(J25:AC25) -> 0 | AF25: =AD25-I25 -> 0 | AG25: =ROUND(H25,2) -> 808.15 | AH25: =ROUND(AG25*0.07,2) -> 56.57 | AI25: =ROUND(AG25*0.03,2) -> 24.24 | AJ25: =ROUND(AG25*0.02,2) -> 16.16 | AK25: =IF(AR25,Y25/(AR25*1.12)*AR25,0) -> 0 | AL25: =ROUND(Y25-AK25,2) -> 0 | AM25: =ROUND(AG25-AK25,2) -> 808.15 | AN25: =ROUND(AM25*0.07,2) -> 56.57 | AO25: =ROUND(AM25*0.03,2) -> 24.24 | AP25: =ROUND(AH25+AI25+AJ25-AL25-AN25-AO25,2) -> 16.16 | AQ25: ="TJ"&A25 -> TJ202512021636000598013 | AR25: =IF(E25="无全额",0,MID(E25,4,2)*1) -> 0.06
A26: 202512021639000011329 | B26: 蚂蚁HRO | C26: 劳务承揽 | D26: 承揽业务 | E26: 专票（6%） | F26: =ROUND(SUMIF([1]开票!$A$2:$A$1750,[1]申请!AQ26,[1]开票!$C$2:$C$1750),2) -> 118324.94 | G26: =ROUND(SUMIF([1]开票!$A$2:$A$1750,[1]申请!AQ26,[1]开票!$D$2:$D$1750),2) -> 0 | H26: =ROUND(SUMIF([1]开票!$A$2:$A$1750,[1]申请!AQ26,[1]开票!$E$2:$E$1750),2) -> 7099.5 | I26: =SUM(F26:H26) -> 125424.44 | J26: 125424.44 | AD26: =SUM(J26:AC26) -> 125424.44 | AE26: =AD26-SUM(J26:AC26) -> 0 | AF26: =AD26-I26 -> 0 | AG26: =ROUND(H26,2) -> 7099.5 | AH26: =ROUND(AG26*0.07,2) -> 496.97 | AI26: =ROUND(AG26*0.03,2) -> 212.99 | AJ26: =ROUND(AG26*0.02,2) -> 141.99 | AK26: =IF(AR26,Y26/(AR26*1.12)*AR26,0) -> 0 | AL26: =ROUND(Y26-AK26,2) -> 0 | AM26: =ROUND(AG26-AK26,2) -> 7099.5 | AN26: =ROUND(AM26*0.07,2) -> 496.97 | AO26: =ROUND(AM26*0.03,2) -> 212.99 | AP26: =ROUND(AH26+AI26+AJ26-AL26-AN26-AO26,2) -> 141.99 | AQ26: ="TJ"&A26 -> TJ202512021639000011329 | AR26: =IF(E26="无全额",0,MID(E26,4,2)*1) -> 0.06
A27: 202512021650000521680 | B27: 蚂蚁HRO | C27: 劳务承揽 | D27: 承揽业务 | E27: 专票（6%） | F27: =ROUND(SUMIF([1]开票!$A$2:$A$1750,[1]申请!AQ27,[1]开票!$C$2:$C$1750),2) -> 12666.22 | G27: =ROUND(SUMIF([1]开票!$A$2:$A$1750,[1]申请!AQ27,[1]开票!$D$2:$D$1750),2) -> 0 | H27: =ROUND(SUMIF([1]开票!$A$2:$A$1750,[1]申请!AQ27,[1]开票!$E$2:$E$1750),2) -> 759.97 | I27: =SUM(F27:H27) -> 13426.19 | J27: 13426.19 | AD27: =SUM(J27:AC27) -> 13426.19 | AE27: =AD27-SUM(J27:AC27) -> 0 | AF27: =AD27-I27 -> 0 | AG27: =ROUND(H27,2) -> 759.97 | AH27: =ROUND(AG27*0.07,2) -> 53.2 | AI27: =ROUND(AG27*0.03,2) -> 22.8 | AJ27: =ROUND(AG27*0.02,2) -> 15.2 | AK27: =IF(AR27,Y27/(AR27*1.12)*AR27,0) -> 0 | AL27: =ROUND(Y27-AK27,2) -> 0 | AM27: =ROUND(AG27-AK27,2) -> 759.97 | AN27: =ROUND(AM27*0.07,2) -> 53.2 | AO27: =ROUND(AM27*0.03,2) -> 22.8 | AP27: =ROUND(AH27+AI27+AJ27-AL27-AN27-AO27,2) -> 15.2 | AQ27: ="TJ"&A27 -> TJ202512021650000521680 | AR27: =IF(E27="无全额",0,MID(E27,4,2)*1) -> 0.06
A28: 202512021653000468302 | B28: 蚂蚁HRO | C28: 劳务承揽 | D28: 承揽业务 | E28: 专票（6%） | F28: =ROUND(SUMIF([1]开票!$A$2:$A$1750,[1]申请!AQ28,[1]开票!$C$2:$C$1750),2) -> 19424.18 | G28: =ROUND(SUMIF([1]开票!$A$2:$A$1750,[1]申请!AQ28,[1]开票!$D$2:$D$1750),2) -> 0 | H28: =ROUND(SUMIF([1]开票!$A$2:$A$1750,[1]申请!AQ28,[1]开票!$E$2:$E$1750),2) -> 1165.45 | I28: =SUM(F28:H28) -> 20589.63 | J28: 20589.63 | AD28: =SUM(J28:AC28) -> 20589.63 | AE28: =AD28-SUM(J28:AC28) -> 0 | AF28: =AD28-I28 -> 0 | AG28: =ROUND(H28,2) -> 1165.45 | AH28: =ROUND(AG28*0.07,2) -> 81.58 | AI28: =ROUND(AG28*0.03,2) -> 34.96 | AJ28: =ROUND(AG28*0.02,2) -> 23.31 | AK28: =IF(AR28,Y28/(AR28*1.12)*AR28,0) -> 0 | AL28: =ROUND(Y28-AK28,2) -> 0 | AM28: =ROUND(AG28-AK28,2) -> 1165.45 | AN28: =ROUND(AM28*0.07,2) -> 81.58 | AO28: =ROUND(AM28*0.03,2) -> 34.96 | AP28: =ROUND(AH28+AI28+AJ28-AL28-AN28-AO28,2) -> 23.31 | AQ28: ="TJ"&A28 -> TJ202512021653000468302 | AR28: =IF(E28="无全额",0,MID(E28,4,2)*1) -> 0.06
A29: 202512021654000236881 | B29: 蚂蚁HRO | C29: 劳务承揽 | D29: 承揽业务 | E29: 专票（6%） | F29: =ROUND(SUMIF([1]开票!$A$2:$A$1750,[1]申请!AQ29,[1]开票!$C$2:$C$1750),2) -> 13932.08 | G29: =ROUND(SUMIF([1]开票!$A$2:$A$1750,[1]申请!AQ29,[1]开票!$D$2:$D$1750),2) -> 0 | H29: =ROUND(SUMIF([1]开票!$A$2:$A$1750,[1]申请!AQ29,[1]开票!$E$2:$E$1750),2) -> 835.92 | I29: =SUM(F29:H29) -> 14768 | J29: 14768 | AD29: =SUM(J29:AC29) -> 14768 | AE29: =AD29-SUM(J29:AC29) -> 0 | AF29: =AD29-I29 -> 0 | AG29: =ROUND(H29,2) -> 835.92 | AH29: =ROUND(AG29*0.07,2) -> 58.51 | AI29: =ROUND(AG29*0.03,2) -> 25.08 | AJ29: =ROUND(AG29*0.02,2) -> 16.72 | AK29: =IF(AR29,Y29/(AR29*1.12)*AR29,0) -> 0 | AL29: =ROUND(Y29-AK29,2) -> 0 | AM29: =ROUND(AG29-AK29,2) -> 835.92 | AN29: =ROUND(AM29*0.07,2) -> 58.51 | AO29: =ROUND(AM29*0.03,2) -> 25.08 | AP29: =ROUND(AH29+AI29+AJ29-AL29-AN29-AO29,2) -> 16.72 | AQ29: ="TJ"&A29 -> TJ202512021654000236881 | AR29: =IF(E29="无全额",0,MID(E29,4,2)*1) -> 0.06
A30: 202512021655000124061 | B30: 北京京东世纪贸易有限公司 | C30: 猎头服务 | D30: 猎头业务 | E30: 专票（6%） | F30: =ROUND(SUMIF([1]开票!$A$2:$A$1750,[1]申请!AQ30,[1]开票!$C$2:$C$1750),2) -> 6132.08 | G30: =ROUND(SUMIF([1]开票!$A$2:$A$1750,[1]申请!AQ30,[1]开票!$D$2:$D$1750),2) -> 0 | H30: =ROUND(SUMIF([1]开票!$A$2:$A$1750,[1]申请!AQ30,[1]开票!$E$2:$E$1750),2) -> 367.92 | I30: =SUM(F30:H30) -> 6500 | N30: 6500 | AD30: =SUM(J30:AC30) -> 6500 | AE30: =AD30-SUM(J30:AC30) -> 0 | AF30: =AD30-I30 -> 0 | AG30: =ROUND(H30,2) -> 367.92 | AH30: =ROUND(AG30*0.07,2) -> 25.75 | AI30: =ROUND(AG30*0.03,2) -> 11.04 | AJ30: =ROUND(AG30*0.02,2) -> 7.36 | AK30: =IF(AR30,Y30/(AR30*1.12)*AR30,0) -> 0 | AL30: =ROUND(Y30-AK30,2) -> 0 | AM30: =ROUND(AG30-AK30,2) -> 367.92 | AN30: =ROUND(AM30*0.07,2) -> 25.75 | AO30: =ROUND(AM30*0.03,2) -> 11.04 | AP30: =ROUND(AH30+AI30+AJ30-AL30-AN30-AO30,2) -> 7.36 | AQ30: ="TJ"&A30 -> TJ202512021655000124061 | AR30: =IF(E30="无全额",0,MID(E30,4,2)*1) -> 0.06
A31: 202512021655000562923 | B31: 蚂蚁HRO | C31: 劳务承揽 | D31: 承揽业务 | E31: 专票（6%） | F31: =ROUND(SUMIF([1]开票!$A$2:$A$1750,[1]申请!AQ31,[1]开票!$C$2:$C$1750),2) -> 2497.15 | G31: =ROUND(SUMIF([1]开票!$A$2:$A$1750,[1]申请!AQ31,[1]开票!$D$2:$D$1750),2) -> 0 | H31: =ROUND(SUMIF([1]开票!$A$2:$A$1750,[1]申请!AQ31,[1]开票!$E$2:$E$1750),2) -> 149.83 | I31: =SUM(F31:H31) -> 2646.98 | J31: 2646.98 | AD31: =SUM(J31:AC31) -> 2646.98 | AE31: =AD31-SUM(J31:AC31) -> 0 | AF31: =AD31-I31 -> 0 | AG31: =ROUND(H31,2) -> 149.83 | AH31: =ROUND(AG31*0.07,2) -> 10.49 | AI31: =ROUND(AG31*0.03,2) -> 4.49 | AJ31: =ROUND(AG31*0.02,2) -> 3 | AK31: =IF(AR31,Y31/(AR31*1.12)*AR31,0) -> 0 | AL31: =ROUND(Y31-AK31,2) -> 0 | AM31: =ROUND(AG31-AK31,2) -> 149.83 | AN31: =ROUND(AM31*0.07,2) -> 10.49 | AO31: =ROUND(AM31*0.03,2) -> 4.49 | AP31: =ROUND(AH31+AI31+AJ31-AL31-AN31-AO31,2) -> 3 | AQ31: ="TJ"&A31 -> TJ202512021655000562923 | AR31: =IF(E31="无全额",0,MID(E31,4,2)*1) -> 0.06
A32: 202512021749000195269 | B32: 广州白云山敬修堂药业股份有限公司 | C32: 劳务承揽 | D32: 承揽业务 | E32: 专票（6%） | F32: =ROUND(SUMIF([1]开票!$A$2:$A$1750,[1]申请!AQ32,[1]开票!$C$2:$C$1750),2) -> 20572.64 | G32: =ROUND(SUMIF([1]开票!$A$2:$A$1750,[1]申请!AQ32,[1]开票!$D$2:$D$1750),2) -> 0 | H32: =ROUND(SUMIF([1]开票!$A$2:$A$1750,[1]申请!AQ32,[1]开票!$E$2:$E$1750),2) -> 1234.36 | I32: =SUM(F32:H32) -> 21807 | L32: 21807 | AD32: =SUM(J32:AC32) -> 21807 | AE32: =AD32-SUM(J32:AC32) -> 0 | AF32: =AD32-I32 -> 0 | AG32: =ROUND(H32,2) -> 1234.36 | AH32: =ROUND(AG32*0.07,2) -> 86.41 | AI32: =ROUND(AG32*0.03,2) -> 37.03 | AJ32: =ROUND(AG32*0.02,2) -> 24.69 | AK32: =IF(AR32,Y32/(AR32*1.12)*AR32,0) -> 0 | AL32: =ROUND(Y32-AK32,2) -> 0 | AM32: =ROUND(AG32-AK32,2) -> 1234.36 | AN32: =ROUND(AM32*0.07,2) -> 86.41 | AO32: =ROUND(AM32*0.03,2) -> 37.03 | AP32: =ROUND(AH32+AI32+AJ32-AL32-AN32-AO32,2) -> 24.69 | AQ32: ="TJ"&A32 -> TJ202512021749000195269 | AR32: =IF(E32="无全额",0,MID(E32,4,2)*1) -> 0.06
A33: 202512031007000000620 | B33: 畅捷通信息技术股份有限公司 | C33: 劳务派遣 | D33: 派遣业务 | E33: 专票（6%） | F33: =ROUND(SUMIF([1]开票!$A$2:$A$1750,[1]申请!AQ33,[1]开票!$C$2:$C$1750),2) -> 227601.17 | G33: =ROUND(SUMIF([1]开票!$A$2:$A$1750,[1]申请!AQ33,[1]开票!$D$2:$D$1750),2) -> 0 | H33: =ROUND(SUMIF([1]开票!$A$2:$A$1750,[1]申请!AQ33,[1]开票!$E$2:$E$1750),2) -> 13656.07 | I33: =SUM(F33:H33) -> 241257.24 | S33: 151930.3 | T33: 50.15 | U33: 44906.29 | V33: 1320 | Y33: 0 | AA33: 43050.5 | AD33: =SUM(J33:AC33) -> 241257.24 | AE33: =AD33-SUM(J33:AC33) -> 0 | AF33: =AD33-I33 -> 0 | AG33: =ROUND(H33,2) -> 13656.07 | AH33: =ROUND(AG33*0.07,2) -> 955.92 | AI33: =ROUND(AG33*0.03,2) -> 409.68 | AJ33: =ROUND(AG33*0.02,2) -> 273.12 | AK33: =IF(AR33,Y33/(AR33*1.12)*AR33,0) -> 0 | AL33: =ROUND(Y33-AK33,2) -> 0 | AM33: =ROUND(AG33-AK33,2) -> 13656.07 | AN33: =ROUND(AM33*0.07,2) -> 955.92 | AO33: =ROUND(AM33*0.03,2) -> 409.68 | AP33: =ROUND(AH33+AI33+AJ33-AL33-AN33-AO33,2) -> 273.12 | AQ33: ="TJ"&A33 -> TJ202512031007000000620 | AR33: =IF(E33="无全额",0,MID(E33,4,2)*1) -> 0.06
A34: 202512031207000266938 | B34: 辉山乳业（沈阳）销售有限公司 | C34: 劳务承揽 | D34: 承揽业务 | E34: 专票（6%） | F34: =ROUND(SUMIF([1]开票!$A$2:$A$1750,[1]申请!AQ34,[1]开票!$C$2:$C$1750),2) -> 5473.52 | G34: =ROUND(SUMIF([1]开票!$A$2:$A$1750,[1]申请!AQ34,[1]开票!$D$2:$D$1750),2) -> 0 | H34: =ROUND(SUMIF([1]开票!$A$2:$A$1750,[1]申请!AQ34,[1]开票!$E$2:$E$1750),2) -> 328.41 | I34: =SUM(F34:H34) -> 5801.93 | L34: 5801.93 | AD34: =SUM(J34:AC34) -> 5801.93 | AE34: =AD34-SUM(J34:AC34) -> 0 | AF34: =AD34-I34 -> 0 | AG34: =ROUND(H34,2) -> 328.41 | AH34: =ROUND(AG34*0.07,2) -> 22.99 | AI34: =ROUND(AG34*0.03,2) -> 9.85 | AJ34: =ROUND(AG34*0.02,2) -> 6.57 | AK34: =IF(AR34,Y34/(AR34*1.12)*AR34,0) -> 0 | AL34: =ROUND(Y34-AK34,2) -> 0 | AM34: =ROUND(AG34-AK34,2) -> 328.41 | AN34: =ROUND(AM34*0.07,2) -> 22.99 | AO34: =ROUND(AM34*0.03,2) -> 9.85 | AP34: =ROUND(AH34+AI34+AJ34-AL34-AN34-AO34,2) -> 6.57 | AQ34: ="TJ"&A34 -> TJ202512031207000266938 | AR34: =IF(E34="无全额",0,MID(E34,4,2)*1) -> 0.06
A35: 202512031357000592545 | B35: 广州市第一中学 | C35: 劳务派遣 | D35: 派遣业务 | E35: 普票（5%） | F35: =ROUND(SUMIF([1]开票!$A$2:$A$1750,[1]申请!AQ35,[1]开票!$C$2:$C$1750),2) -> 0 | G35: =ROUND(SUMIF([1]开票!$A$2:$A$1750,[1]申请!AQ35,[1]开票!$D$2:$D$1750),2) -> 40870 | H35: =ROUND(SUMIF([1]开票!$A$2:$A$1750,[1]申请!AQ35,[1]开票!$E$2:$E$1750),2) -> 0 | I35: =SUM(F35:H35) -> 40870 | K35: 0 | S35: 40870 | T35: 0 | U35: 0 | V35: 0 | X35: 0 | AD35: =SUM(J35:AC35) -> 40870 | AE35: =AD35-SUM(J35:AC35) -> 0 | AF35: =AD35-I35 -> 0 | AG35: =ROUND(H35,2) -> 0 | AH35: =ROUND(AG35*0.07,2) -> 0 | AI35: =ROUND(AG35*0.03,2) -> 0 | AJ35: =ROUND(AG35*0.02,2) -> 0 | AK35: =IF(AR35,Y35/(AR35*1.12)*AR35,0) -> 0 | AL35: =ROUND(Y35-AK35,2) -> 0 | AM35: =ROUND(AG35-AK35,2) -> 0 | AN35: =ROUND(AM35*0.07,2) -> 0 | AO35: =ROUND(AM35*0.03,2) -> 0 | AP35: =ROUND(AH35+AI35+AJ35-AL35-AN35-AO35,2) -> 0 | AQ35: ="TJ"&A35 -> TJ202512031357000592545 | AR35: =IF(E35="无全额",0,MID(E35,4,2)*1) -> 0.05
A36: 202512031410000212031 | B36: 广州市第一中学 | C36: 劳务派遣 | D36: 派遣业务 | E36: 普票（5%） | F36: =ROUND(SUMIF([1]开票!$A$2:$A$1750,[1]申请!AQ36,[1]开票!$C$2:$C$1750),2) -> 2228.57 | G36: =ROUND(SUMIF([1]开票!$A$2:$A$1750,[1]申请!AQ36,[1]开票!$D$2:$D$1750),2) -> 263840.73 | H36: =ROUND(SUMIF([1]开票!$A$2:$A$1750,[1]申请!AQ36,[1]开票!$E$2:$E$1750),2) -> 111.43 | I36: =SUM(F36:H36) -> 266180.73 | K36: 2340 | S36: 169028.62 | T36: 262.85 | U36: 71919.66 | V36: 21042 | X36: 1587.6 | AD36: =SUM(J36:AC36) -> 266180.73 | AE36: =AD36-SUM(J36:AC36) -> 0 | AF36: =AD36-I36 -> 0 | AG36: =ROUND(H36,2) -> 111.43 | AH36: =ROUND(AG36*0.07,2) -> 7.8 | AI36: =ROUND(AG36*0.03,2) -> 3.34 | AJ36: =ROUND(AG36*0.02,2) -> 2.23 | AK36: =IF(AR36,Y36/(AR36*1.12)*AR36,0) -> 0 | AL36: =ROUND(Y36-AK36,2) -> 0 | AM36: =ROUND(AG36-AK36,2) -> 111.43 | AN36: =ROUND(AM36*0.07,2) -> 7.8 | AO36: =ROUND(AM36*0.03,2) -> 3.34 | AP36: =ROUND(AH36+AI36+AJ36-AL36-AN36-AO36,2) -> 2.23 | AQ36: ="TJ"&A36 -> TJ202512031410000212031 | AR36: =IF(E36="无全额",0,MID(E36,4,2)*1) -> 0.05
A37: 202512031411000228772 | B37: 广州市第一中学 | C37: 劳务派遣 | D37: 派遣业务 | E37: 专票（6%） | F37: =ROUND(SUMIF([1]开票!$A$2:$A$1750,[1]申请!AQ37,[1]开票!$C$2:$C$1750),2) -> 35.85 | G37: =ROUND(SUMIF([1]开票!$A$2:$A$1750,[1]申请!AQ37,[1]开票!$D$2:$D$1750),2) -> 0 | H37: =ROUND(SUMIF([1]开票!$A$2:$A$1750,[1]申请!AQ37,[1]开票!$E$2:$E$1750),2) -> 2.15 | I37: =SUM(F37:H37) -> 38 | P37: 11 | W37: 27 | AD37: =SUM(J37:AC37) -> 38 | AE37: =AD37-SUM(J37:AC37) -> 0 | AF37: =AD37-I37 -> 0 | AG37: =ROUND(H37,2) -> 2.15 | AH37: =ROUND(AG37*0.07,2) -> 0.15 | AI37: =ROUND(AG37*0.03,2) -> 0.06 | AJ37: =ROUND(AG37*0.02,2) -> 0.04 | AK37: =IF(AR37,Y37/(AR37*1.12)*AR37,0) -> 0 | AL37: =ROUND(Y37-AK37,2) -> 0 | AM37: =ROUND(AG37-AK37,2) -> 2.15 | AN37: =ROUND(AM37*0.07,2) -> 0.15 | AO37: =ROUND(AM37*0.03,2) -> 0.06 | AP37: =ROUND(AH37+AI37+AJ37-AL37-AN37-AO37,2) -> 0.04 | AQ37: ="TJ"&A37 -> TJ202512031411000228772 | AR37: =IF(E37="无全额",0,MID(E37,4,2)*1) -> 0.06
A38: 202512031527000358276 | B38: 蚂蚁HRO | C38: 劳务承揽 | D38: 承揽业务 | E38: 专票（6%） | F38: =ROUND(SUMIF([1]开票!$A$2:$A$1750,[1]申请!AQ38,[1]开票!$C$2:$C$1750),2) -> 14639.37 | G38: =ROUND(SUMIF([1]开票!$A$2:$A$1750,[1]申请!AQ38,[1]开票!$D$2:$D$1750),2) -> 0 | H38: =ROUND(SUMIF([1]开票!$A$2:$A$1750,[1]申请!AQ38,[1]开票!$E$2:$E$1750),2) -> 878.36 | I38: =SUM(F38:H38) -> 15517.73 | J38: 15517.73 | AD38: =SUM(J38:AC38) -> 15517.73 | AE38: =AD38-SUM(J38:AC38) -> 0 | AF38: =AD38-I38 -> 0 | AG38: =ROUND(H38,2) -> 878.36 | AH38: =ROUND(AG38*0.07,2) -> 61.49 | AI38: =ROUND(AG38*0.03,2) -> 26.35 | AJ38: =ROUND(AG38*0.02,2) -> 17.57 | AK38: =IF(AR38,Y38/(AR38*1.12)*AR38,0) -> 0 | AL38: =ROUND(Y38-AK38,2) -> 0 | AM38: =ROUND(AG38-AK38,2) -> 878.36 | AN38: =ROUND(AM38*0.07,2) -> 61.49 | AO38: =ROUND(AM38*0.03,2) -> 26.35 | AP38: =ROUND(AH38+AI38+AJ38-AL38-AN38-AO38,2) -> 17.57 | AQ38: ="TJ"&A38 -> TJ202512031527000358276 | AR38: =IF(E38="无全额",0,MID(E38,4,2)*1) -> 0.06
A39: 202512031546000048920 | B39: 广汽传祺汽车销售有限公司 | C39: 劳务承揽 | D39: 小时间承揽 | E39: 普票（6%） | F39: =ROUND(SUMIF([1]开票!$A$2:$A$1750,[1]申请!AQ39,[1]开票!$C$2:$C$1750),2) -> 801132.08 | G39: =ROUND(SUMIF([1]开票!$A$2:$A$1750,[1]申请!AQ39,[1]开票!$D$2:$D$1750),2) -> 0 | H39: =ROUND(SUMIF([1]开票!$A$2:$A$1750,[1]申请!AQ39,[1]开票!$E$2:$E$1750),2) -> 48067.92 | I39: =SUM(F39:H39) -> 849200 | L39: 48066.13 | S39: 801133.87 | AD39: =SUM(J39:AC39) -> 849200 | AE39: =AD39-SUM(J39:AC39) -> 0 | AF39: =AD39-I39 -> 0 | AG39: =ROUND(H39,2) -> 48067.92 | AH39: =ROUND(AG39*0.07,2) -> 3364.75 | AI39: =ROUND(AG39*0.03,2) -> 1442.04 | AJ39: =ROUND(AG39*0.02,2) -> 961.36 | AK39: =IF(AR39,Y39/(AR39*1.12)*AR39,0) -> 0 | AL39: =ROUND(Y39-AK39,2) -> 0 | AM39: =ROUND(AG39-AK39,2) -> 48067.92 | AN39: =ROUND(AM39*0.07,2) -> 3364.75 | AO39: =ROUND(AM39*0.03,2) -> 1442.04 | AP39: =ROUND(AH39+AI39+AJ39-AL39-AN39-AO39,2) -> 961.36 | AQ39: ="TJ"&A39 -> TJ202512031546000048920 | AR39: =IF(E39="无全额",0,MID(E39,4,2)*1) -> 0.06
A40: 202512031618000265075 | B40: 优湃能源科技（广州）有限公司 | C40: 劳务承揽 | D40: 承揽业务 | E40: 专票（6%） | F40: =ROUND(SUMIF([1]开票!$A$2:$A$1750,[1]申请!AQ40,[1]开票!$C$2:$C$1750),2) -> 350842.08 | G40: =ROUND(SUMIF([1]开票!$A$2:$A$1750,[1]申请!AQ40,[1]开票!$D$2:$D$1750),2) -> 0 | H40: =ROUND(SUMIF([1]开票!$A$2:$A$1750,[1]申请!AQ40,[1]开票!$E$2:$E$1750),2) -> 21050.52 | I40: =SUM(F40:H40) -> 371892.6 | L40: 371892.6 | AD40: =SUM(J40:AC40) -> 371892.6 | AE40: =AD40-SUM(J40:AC40) -> 0 | AF40: =AD40-I40 -> 0 | AG40: =ROUND(H40,2) -> 21050.52 | AH40: =ROUND(AG40*0.07,2) -> 1473.54 | AI40: =ROUND(AG40*0.03,2) -> 631.52 | AJ40: =ROUND(AG40*0.02,2) -> 421.01 | AK40: =IF(AR40,Y40/(AR40*1.12)*AR40,0) -> 0 | AL40: =ROUND(Y40-AK40,2) -> 0 | AM40: =ROUND(AG40-AK40,2) -> 21050.52 | AN40: =ROUND(AM40*0.07,2) -> 1473.54 | AO40: =ROUND(AM40*0.03,2) -> 631.52 | AP40: =ROUND(AH40+AI40+AJ40-AL40-AN40-AO40,2) -> 421.01 | AQ40: ="TJ"&A40 -> TJ202512031618000265075 | AR40: =IF(E40="无全额",0,MID(E40,4,2)*1) -> 0.06
A41: 202512031746000005828 | B41: 广电计量 | C41: 劳务派遣 | D41: 派遣业务 | E41: 专票（5%） | F41: =ROUND(SUMIF([1]开票!$A$2:$A$1750,[1]申请!AQ41,[1]开票!$C$2:$C$1750),2) -> 175.36 | G41: =ROUND(SUMIF([1]开票!$A$2:$A$1750,[1]申请!AQ41,[1]开票!$D$2:$D$1750),2) -> 15483.78 | H41: =ROUND(SUMIF([1]开票!$A$2:$A$1750,[1]申请!AQ41,[1]开票!$E$2:$E$1750),2) -> 8.77 | I41: =SUM(F41:H41) -> 15667.91 | J41: 184.13 | S41: 11735.37 | T41: 83.1 | U41: 3415.31 | V41: 250 | AD41: =SUM(J41:AC41) -> 15667.91 | AE41: =AD41-SUM(J41:AC41) -> 0 | AF41: =AD41-I41 -> 0 | AG41: =ROUND(H41,2) -> 8.77 | AH41: =ROUND(AG41*0.07,2) -> 0.61 | AI41: =ROUND(AG41*0.03,2) -> 0.26 | AJ41: =ROUND(AG41*0.02,2) -> 0.18 | AK41: =IF(AR41,Y41/(AR41*1.12)*AR41,0) -> 0 | AL41: =ROUND(Y41-AK41,2) -> 0 | AM41: =ROUND(AG41-AK41,2) -> 8.77 | AN41: =ROUND(AM41*0.07,2) -> 0.61 | AO41: =ROUND(AM41*0.03,2) -> 0.26 | AP41: =ROUND(AH41+AI41+AJ41-AL41-AN41-AO41,2) -> 0.18 | AQ41: ="TJ"&A41 -> TJ202512031746000005828 | AR41: =IF(E41="无全额",0,MID(E41,4,2)*1) -> 0.05
A42: 202512032027000073341 | B42: 广东-富凌食品（BPO） | C42: 劳务承揽 | D42: 承揽业务 | E42: 专票（6%） | F42: =ROUND(SUMIF([1]开票!$A$2:$A$1750,[1]申请!AQ42,[1]开票!$C$2:$C$1750),2) -> 342970.46 | G42: =ROUND(SUMIF([1]开票!$A$2:$A$1750,[1]申请!AQ42,[1]开票!$D$2:$D$1750),2) -> 0 | H42: =ROUND(SUMIF([1]开票!$A$2:$A$1750,[1]申请!AQ42,[1]开票!$E$2:$E$1750),2) -> 20578.23 | I42: =SUM(F42:H42) -> 363548.69 | L42: 363548.69 | AD42: =SUM(J42:AC42) -> 363548.69 | AE42: =AD42-SUM(J42:AC42) -> 0 | AF42: =AD42-I42 -> 0 | AG42: =ROUND(H42,2) -> 20578.23 | AH42: =ROUND(AG42*0.07,2) -> 1440.48 | AI42: =ROUND(AG42*0.03,2) -> 617.35 | AJ42: =ROUND(AG42*0.02,2) -> 411.56 | AK42: =IF(AR42,Y42/(AR42*1.12)*AR42,0) -> 0 | AL42: =ROUND(Y42-AK42,2) -> 0 | AM42: =ROUND(AG42-AK42,2) -> 20578.23 | AN42: =ROUND(AM42*0.07,2) -> 1440.48 | AO42: =ROUND(AM42*0.03,2) -> 617.35 | AP42: =ROUND(AH42+AI42+AJ42-AL42-AN42-AO42,2) -> 411.56 | AQ42: ="TJ"&A42 -> TJ202512032027000073341 | AR42: =IF(E42="无全额",0,MID(E42,4,2)*1) -> 0.06
A43: 202512032033000569623 | B43: 广东-智慧城市（劳务外包） | C43: 劳务承揽 | D43: 承揽业务 | E43: 专票（6%） | F43: =ROUND(SUMIF([1]开票!$A$2:$A$1750,[1]申请!AQ43,[1]开票!$C$2:$C$1750),2) -> 2830.19 | G43: =ROUND(SUMIF([1]开票!$A$2:$A$1750,[1]申请!AQ43,[1]开票!$D$2:$D$1750),2) -> 0 | H43: =ROUND(SUMIF([1]开票!$A$2:$A$1750,[1]申请!AQ43,[1]开票!$E$2:$E$1750),2) -> 169.81 | I43: =SUM(F43:H43) -> 3000 | L43: 3000 | AD43: =SUM(J43:AC43) -> 3000 | AE43: =AD43-SUM(J43:AC43) -> 0 | AF43: =AD43-I43 -> 0 | AG43: =ROUND(H43,2) -> 169.81 | AH43: =ROUND(AG43*0.07,2) -> 11.89 | AI43: =ROUND(AG43*0.03,2) -> 5.09 | AJ43: =ROUND(AG43*0.02,2) -> 3.4 | AK43: =IF(AR43,Y43/(AR43*1.12)*AR43,0) -> 0 | AL43: =ROUND(Y43-AK43,2) -> 0 | AM43: =ROUND(AG43-AK43,2) -> 169.81 | AN43: =ROUND(AM43*0.07,2) -> 11.89 | AO43: =ROUND(AM43*0.03,2) -> 5.09 | AP43: =ROUND(AH43+AI43+AJ43-AL43-AN43-AO43,2) -> 3.4 | AQ43: ="TJ"&A43 -> TJ202512032033000569623 | AR43: =IF(E43="无全额",0,MID(E43,4,2)*1) -> 0.06
A44: 202512041106000591442 | B44: 黑龙江九州通医药有限公司 | C44: 人力资源外包（代理） | D44: 代理业务 | E44: 专票（6%） | F44: =ROUND(SUMIF([1]开票!$A$2:$A$1750,[1]申请!AQ44,[1]开票!$C$2:$C$1750),2) -> 31358.49 | G44: =ROUND(SUMIF([1]开票!$A$2:$A$1750,[1]申请!AQ44,[1]开票!$D$2:$D$1750),2) -> 0 | H44: =ROUND(SUMIF([1]开票!$A$2:$A$1750,[1]申请!AQ44,[1]开票!$E$2:$E$1750),2) -> 1881.51 | I44: =SUM(F44:H44) -> 33240 | L44: 33240 | AD44: =SUM(J44:AC44) -> 33240 | AE44: =AD44-SUM(J44:AC44) -> 0 | AF44: =AD44-I44 -> 0 | AG44: =ROUND(H44,2) -> 1881.51 | AH44: =ROUND(AG44*0.07,2) -> 131.71 | AI44: =ROUND(AG44*0.03,2) -> 56.45 | AJ44: =ROUND(AG44*0.02,2) -> 37.63 | AK44: =IF(AR44,Y44/(AR44*1.12)*AR44,0) -> 0 | AL44: =ROUND(Y44-AK44,2) -> 0 | AM44: =ROUND(AG44-AK44,2) -> 1881.51 | AN44: =ROUND(AM44*0.07,2) -> 131.71 | AO44: =ROUND(AM44*0.03,2) -> 56.45 | AP44: =ROUND(AH44+AI44+AJ44-AL44-AN44-AO44,2) -> 37.63 | AQ44: ="TJ"&A44 -> TJ202512041106000591442 | AR44: =IF(E44="无全额",0,MID(E44,4,2)*1) -> 0.06
A45: 202512041108000555761 | B45: 华润电力（广东）能源服务有限公司 | C45: 劳务派遣 | D45: 派遣业务 | E45: 专票（5%） | F45: =ROUND(SUMIF([1]开票!$A$2:$A$1750,[1]申请!AQ45,[1]开票!$C$2:$C$1750),2) -> 1262.86 | G45: =ROUND(SUMIF([1]开票!$A$2:$A$1750,[1]申请!AQ45,[1]开票!$D$2:$D$1750),2) -> 922694.92 | H45: =ROUND(SUMIF([1]开票!$A$2:$A$1750,[1]申请!AQ45,[1]开票!$E$2:$E$1750),2) -> 63.14 | I45: =SUM(F45:H45) -> 924020.92 | J45: 1326 | S45: 725718.99 | T45: 26691.68 | U45: 114124.25 | V45: 56160 | W45: 0 | AD45: =SUM(J45:AC45) -> 924020.92 | AE45: =AD45-SUM(J45:AC45) -> 0 | AF45: =AD45-I45 -> 0 | AG45: =ROUND(H45,2) -> 63.14 | AH45: =ROUND(AG45*0.07,2) -> 4.42 | AI45: =ROUND(AG45*0.03,2) -> 1.89 | AJ45: =ROUND(AG45*0.02,2) -> 1.26 | AK45: =IF(AR45,Y45/(AR45*1.12)*AR45,0) -> 0 | AL45: =ROUND(Y45-AK45,2) -> 0 | AM45: =ROUND(AG45-AK45,2) -> 63.14 | AN45: =ROUND(AM45*0.07,2) -> 4.42 | AO45: =ROUND(AM45*0.03,2) -> 1.89 | AP45: =ROUND(AH45+AI45+AJ45-AL45-AN45-AO45,2) -> 1.26 | AQ45: ="TJ"&A45 -> TJ202512041108000555761 | AR45: =IF(E45="无全额",0,MID(E45,4,2)*1) -> 0.05
A46: 202512041109000269378 | B46: 美的集团（上海）有限公司 | C46: 劳务承揽 | D46: 派遣业务 | E46: 专票（6%） | F46: =ROUND(SUMIF([1]开票!$A$2:$A$1750,[1]申请!AQ46,[1]开票!$C$2:$C$1750),2) -> 496539.97 | G46: =ROUND(SUMIF([1]开票!$A$2:$A$1750,[1]申请!AQ46,[1]开票!$D$2:$D$1750),2) -> 0 | H46: =ROUND(SUMIF([1]开票!$A$2:$A$1750,[1]申请!AQ46,[1]开票!$E$2:$E$1750),2) -> 29792.4 | I46: =SUM(F46:H46) -> 526332.37 | L46: 526332.37 | AD46: =SUM(J46:AC46) -> 526332.37 | AE46: =AD46-SUM(J46:AC46) -> 0 | AF46: =AD46-I46 -> 0 | AG46: =ROUND(H46,2) -> 29792.4 | AH46: =ROUND(AG46*0.07,2) -> 2085.47 | AI46: =ROUND(AG46*0.03,2) -> 893.77 | AJ46: =ROUND(AG46*0.02,2) -> 595.85 | AK46: =IF(AR46,Y46/(AR46*1.12)*AR46,0) -> 0 | AL46: =ROUND(Y46-AK46,2) -> 0 | AM46: =ROUND(AG46-AK46,2) -> 29792.4 | AN46: =ROUND(AM46*0.07,2) -> 2085.47 | AO46: =ROUND(AM46*0.03,2) -> 893.77 | AP46: =ROUND(AH46+AI46+AJ46-AL46-AN46-AO46,2) -> 595.85 | AQ46: ="TJ"&A46 -> TJ202512041109000269378 | AR46: =IF(E46="无全额",0,MID(E46,4,2)*1) -> 0.06
A47: 202512041150000191842 | B47: 上海移远通信技术股份有限公司 | C47: 劳务承揽 | D47: 承揽业务 | E47: 专票（6%） | F47: =ROUND(SUMIF([1]开票!$A$2:$A$1750,[1]申请!AQ47,[1]开票!$C$2:$C$1750),2) -> 33229.98 | G47: =ROUND(SUMIF([1]开票!$A$2:$A$1750,[1]申请!AQ47,[1]开票!$D$2:$D$1750),2) -> 0 | H47: =ROUND(SUMIF([1]开票!$A$2:$A$1750,[1]申请!AQ47,[1]开票!$E$2:$E$1750),2) -> 1993.8 | I47: =SUM(F47:H47) -> 35223.78 | L47: 35223.78 | AD47: =SUM(J47:AC47) -> 35223.78 | AE47: =AD47-SUM(J47:AC47) -> 0 | AF47: =AD47-I47 -> 0 | AG47: =ROUND(H47,2) -> 1993.8 | AH47: =ROUND(AG47*0.07,2) -> 139.57 | AI47: =ROUND(AG47*0.03,2) -> 59.81 | AJ47: =ROUND(AG47*0.02,2) -> 39.88 | AK47: =IF(AR47,Y47/(AR47*1.12)*AR47,0) -> 0 | AL47: =ROUND(Y47-AK47,2) -> 0 | AM47: =ROUND(AG47-AK47,2) -> 1993.8 | AN47: =ROUND(AM47*0.07,2) -> 139.57 | AO47: =ROUND(AM47*0.03,2) -> 59.81 | AP47: =ROUND(AH47+AI47+AJ47-AL47-AN47-AO47,2) -> 39.88 | AQ47: ="TJ"&A47 -> TJ202512041150000191842 | AR47: =IF(E47="无全额",0,MID(E47,4,2)*1) -> 0.06
A48: 202512041449000118757 | B48: 广药黑龙江医药有限公司 | C48: 劳务派遣 | D48: 派遣业务 | E48: 专票（6%） | F48: =ROUND(SUMIF([1]开票!$A$2:$A$1750,[1]申请!AQ48,[1]开票!$C$2:$C$1750),2) -> 79121.8 | G48: =ROUND(SUMIF([1]开票!$A$2:$A$1750,[1]申请!AQ48,[1]开票!$D$2:$D$1750),2) -> 0 | H48: =ROUND(SUMIF([1]开票!$A$2:$A$1750,[1]申请!AQ48,[1]开票!$E$2:$E$1750),2) -> 4747.31 | I48: =SUM(F48:H48) -> 83869.11 | J48: 4756.95 | L48: 524.16 | S48: 53440.3 | U48: 19387.7 | V48: 5760 | AD48: =SUM(J48:AC48) -> 83869.11 | AE48: =AD48-SUM(J48:AC48) -> 0 | AF48: =AD48-I48 -> 0 | AG48: =ROUND(H48,2) -> 4747.31 | AH48: =ROUND(AG48*0.07,2) -> 332.31 | AI48: =ROUND(AG48*0.03,2) -> 142.42 | AJ48: =ROUND(AG48*0.02,2) -> 94.95 | AK48: =IF(AR48,Y48/(AR48*1.12)*AR48,0) -> 0 | AL48: =ROUND(Y48-AK48,2) -> 0 | AM48: =ROUND(AG48-AK48,2) -> 4747.31 | AN48: =ROUND(AM48*0.07,2) -> 332.31 | AO48: =ROUND(AM48*0.03,2) -> 142.42 | AP48: =ROUND(AH48+AI48+AJ48-AL48-AN48-AO48,2) -> 94.95 | AQ48: ="TJ"&A48 -> TJ202512041449000118757 | AR48: =IF(E48="无全额",0,MID(E48,4,2)*1) -> 0.06
A49: 202512041457000012958 | B49: 平云小匠 | C49: 技术服务 | D49: 小时间承揽 | E49: 专票（6%） | F49: =ROUND(SUMIF([1]开票!$A$2:$A$1750,[1]申请!AQ49,[1]开票!$C$2:$C$1750),2) -> 26277.2 | G49: =ROUND(SUMIF([1]开票!$A$2:$A$1750,[1]申请!AQ49,[1]开票!$D$2:$D$1750),2) -> 0 | H49: =ROUND(SUMIF([1]开票!$A$2:$A$1750,[1]申请!AQ49,[1]开票!$E$2:$E$1750),2) -> 1576.63 | I49: =SUM(F49:H49) -> 27853.83 | Q49: 1392.83 | Z49: 26461 | AD49: =SUM(J49:AC49) -> 27853.83 | AE49: =AD49-SUM(J49:AC49) -> 0 | AF49: =AD49-I49 -> 0 | AG49: =ROUND(H49,2) -> 1576.63 | AH49: =ROUND(AG49*0.07,2) -> 110.36 | AI49: =ROUND(AG49*0.03,2) -> 47.3 | AJ49: =ROUND(AG49*0.02,2) -> 31.53 | AK49: =IF(AR49,Y49/(AR49*1.12)*AR49,0) -> 0 | AL49: =ROUND(Y49-AK49,2) -> 0 | AM49: =ROUND(AG49-AK49,2) -> 1576.63 | AN49: =ROUND(AM49*0.07,2) -> 110.36 | AO49: =ROUND(AM49*0.03,2) -> 47.3 | AP49: =ROUND(AH49+AI49+AJ49-AL49-AN49-AO49,2) -> 31.53 | AQ49: ="TJ"&A49 -> TJ202512041457000012958 | AR49: =IF(E49="无全额",0,MID(E49,4,2)*1) -> 0.06
A50: 202512041458000435054 | B50: 蚂蚁HRO | C50: 劳务承揽 | D50: 承揽业务 | E50: 专票（6%） | F50: =ROUND(SUMIF([1]开票!$A$2:$A$1750,[1]申请!AQ50,[1]开票!$C$2:$C$1750),2) -> 68697.25 | G50: =ROUND(SUMIF([1]开票!$A$2:$A$1750,[1]申请!AQ50,[1]开票!$D$2:$D$1750),2) -> 0 | H50: =ROUND(SUMIF([1]开票!$A$2:$A$1750,[1]申请!AQ50,[1]开票!$E$2:$E$1750),2) -> 4121.84 | I50: =SUM(F50:H50) -> 72819.09 | J50: 72819.09 | AD50: =SUM(J50:AC50) -> 72819.09 | AE50: =AD50-SUM(J50:AC50) -> 0 | AF50: =AD50-I50 -> 0 | AG50: =ROUND(H50,2) -> 4121.84 | AH50: =ROUND(AG50*0.07,2) -> 288.53 | AI50: =ROUND(AG50*0.03,2) -> 123.66 | AJ50: =ROUND(AG50*0.02,2) -> 82.44 | AK50: =IF(AR50,Y50/(AR50*1.12)*AR50,0) -> 0 | AL50: =ROUND(Y50-AK50,2) -> 0 | AM50: =ROUND(AG50-AK50,2) -> 4121.84 | AN50: =ROUND(AM50*0.07,2) -> 288.53 | AO50: =ROUND(AM50*0.03,2) -> 123.66 | AP50: =ROUND(AH50+AI50+AJ50-AL50-AN50-AO50,2) -> 82.44 | AQ50: ="TJ"&A50 -> TJ202512041458000435054 | AR50: =IF(E50="无全额",0,MID(E50,4,2)*1) -> 0.06
A51: 202512041505000295118 | B51: 蚂蚁HRO | C51: 劳务承揽 | D51: 承揽业务 | E51: 专票（6%） | F51: =ROUND(SUMIF([1]开票!$A$2:$A$1750,[1]申请!AQ51,[1]开票!$C$2:$C$1750),2) -> 70.75 | G51: =ROUND(SUMIF([1]开票!$A$2:$A$1750,[1]申请!AQ51,[1]开票!$D$2:$D$1750),2) -> 0 | H51: =ROUND(SUMIF([1]开票!$A$2:$A$1750,[1]申请!AQ51,[1]开票!$E$2:$E$1750),2) -> 4.25 | I51: =SUM(F51:H51) -> 75 | J51: 75 | AD51: =SUM(J51:AC51) -> 75 | AE51: =AD51-SUM(J51:AC51) -> 0 | AF51: =AD51-I51 -> 0 | AG51: =ROUND(H51,2) -> 4.25 | AH51: =ROUND(AG51*0.07,2) -> 0.3 | AI51: =ROUND(AG51*0.03,2) -> 0.13 | AJ51: =ROUND(AG51*0.02,2) -> 0.09 | AK51: =IF(AR51,Y51/(AR51*1.12)*AR51,0) -> 0 | AL51: =ROUND(Y51-AK51,2) -> 0 | AM51: =ROUND(AG51-AK51,2) -> 4.25 | AN51: =ROUND(AM51*0.07,2) -> 0.3 | AO51: =ROUND(AM51*0.03,2) -> 0.13 | AP51: =ROUND(AH51+AI51+AJ51-AL51-AN51-AO51,2) -> 0.09 | AQ51: ="TJ"&A51 -> TJ202512041505000295118 | AR51: =IF(E51="无全额",0,MID(E51,4,2)*1) -> 0.06
A52: 202512041506000079112 | B52: 蚂蚁HRO | C52: 劳务承揽 | D52: 承揽业务 | E52: 专票（6%） | F52: =ROUND(SUMIF([1]开票!$A$2:$A$1750,[1]申请!AQ52,[1]开票!$C$2:$C$1750),2) -> 488198.87 | G52: =ROUND(SUMIF([1]开票!$A$2:$A$1750,[1]申请!AQ52,[1]开票!$D$2:$D$1750),2) -> 0 | H52: =ROUND(SUMIF([1]开票!$A$2:$A$1750,[1]申请!AQ52,[1]开票!$E$2:$E$1750),2) -> 29291.93 | I52: =SUM(F52:H52) -> 517490.8 | J52: 517490.8 | AD52: =SUM(J52:AC52) -> 517490.8 | AE52: =AD52-SUM(J52:AC52) -> 0 | AF52: =AD52-I52 -> 0 | AG52: =ROUND(H52,2) -> 29291.93 | AH52: =ROUND(AG52*0.07,2) -> 2050.44 | AI52: =ROUND(AG52*0.03,2) -> 878.76 | AJ52: =ROUND(AG52*0.02,2) -> 585.84 | AK52: =IF(AR52,Y52/(AR52*1.12)*AR52,0) -> 0 | AL52: =ROUND(Y52-AK52,2) -> 0 | AM52: =ROUND(AG52-AK52,2) -> 29291.93 | AN52: =ROUND(AM52*0.07,2) -> 2050.44 | AO52: =ROUND(AM52*0.03,2) -> 878.76 | AP52: =ROUND(AH52+AI52+AJ52-AL52-AN52-AO52,2) -> 585.84 | AQ52: ="TJ"&A52 -> TJ202512041506000079112 | AR52: =IF(E52="无全额",0,MID(E52,4,2)*1) -> 0.06
A53: 202512041506000359072 | B53: 蚂蚁HRO | C53: 劳务承揽 | D53: 承揽业务 | E53: 专票（6%） | F53: =ROUND(SUMIF([1]开票!$A$2:$A$1750,[1]申请!AQ53,[1]开票!$C$2:$C$1750),2) -> 1464113.4 | G53: =ROUND(SUMIF([1]开票!$A$2:$A$1750,[1]申请!AQ53,[1]开票!$D$2:$D$1750),2) -> 0 | H53: =ROUND(SUMIF([1]开票!$A$2:$A$1750,[1]申请!AQ53,[1]开票!$E$2:$E$1750),2) -> 87846.8 | I53: =SUM(F53:H53) -> 1551960.2 | J53: 1551960.2 | AD53: =SUM(J53:AC53) -> 1551960.2 | AE53: =AD53-SUM(J53:AC53) -> 0 | AF53: =AD53-I53 -> 0 | AG53: =ROUND(H53,2) -> 87846.8 | AH53: =ROUND(AG53*0.07,2) -> 6149.28 | AI53: =ROUND(AG53*0.03,2) -> 2635.4 | AJ53: =ROUND(AG53*0.02,2) -> 1756.94 | AK53: =IF(AR53,Y53/(AR53*1.12)*AR53,0) -> 0 | AL53: =ROUND(Y53-AK53,2) -> 0 | AM53: =ROUND(AG53-AK53,2) -> 87846.8 | AN53: =ROUND(AM53*0.07,2) -> 6149.28 | AO53: =ROUND(AM53*0.03,2) -> 2635.4 | AP53: =ROUND(AH53+AI53+AJ53-AL53-AN53-AO53,2) -> 1756.94 | AQ53: ="TJ"&A53 -> TJ202512041506000359072 | AR53: =IF(E53="无全额",0,MID(E53,4,2)*1) -> 0.06
A54: 202512041507000523293 | B54: 蚂蚁HRO | C54: 劳务承揽 | D54: 承揽业务 | E54: 专票（6%） | F54: =ROUND(SUMIF([1]开票!$A$2:$A$1750,[1]申请!AQ54,[1]开票!$C$2:$C$1750),2) -> 7292.12 | G54: =ROUND(SUMIF([1]开票!$A$2:$A$1750,[1]申请!AQ54,[1]开票!$D$2:$D$1750),2) -> 0 | H54: =ROUND(SUMIF([1]开票!$A$2:$A$1750,[1]申请!AQ54,[1]开票!$E$2:$E$1750),2) -> 437.53 | I54: =SUM(F54:H54) -> 7729.65 | J54: 7729.65 | AD54: =SUM(J54:AC54) -> 7729.65 | AE54: =AD54-SUM(J54:AC54) -> 0 | AF54: =AD54-I54 -> 0 | AG54: =ROUND(H54,2) -> 437.53 | AH54: =ROUND(AG54*0.07,2) -> 30.63 | AI54: =ROUND(AG54*0.03,2) -> 13.13 | AJ54: =ROUND(AG54*0.02,2) -> 8.75 | AK54: =IF(AR54,Y54/(AR54*1.12)*AR54,0) -> 0 | AL54: =ROUND(Y54-AK54,2) -> 0 | AM54: =ROUND(AG54-AK54,2) -> 437.53 | AN54: =ROUND(AM54*0.07,2) -> 30.63 | AO54: =ROUND(AM54*0.03,2) -> 13.13 | AP54: =ROUND(AH54+AI54+AJ54-AL54-AN54-AO54,2) -> 8.75 | AQ54: ="TJ"&A54 -> TJ202512041507000523293 | AR54: =IF(E54="无全额",0,MID(E54,4,2)*1) -> 0.06
A55: 202512041519000546618 | B55: 施启乐（广州）仪器有限公司 | C55: 劳务派遣 | D55: 派遣业务 | E55: 专票（5%） | F55: =ROUND(SUMIF([1]开票!$A$2:$A$1750,[1]申请!AQ55,[1]开票!$C$2:$C$1750),2) -> 2857.14 | G55: =ROUND(SUMIF([1]开票!$A$2:$A$1750,[1]申请!AQ55,[1]开票!$D$2:$D$1750),2) -> 140180.43 | H55: =ROUND(SUMIF([1]开票!$A$2:$A$1750,[1]申请!AQ55,[1]开票!$E$2:$E$1750),2) -> 142.86 | I55: =SUM(F55:H55) -> 143180.43 | J55: 3000 | S55: 80011.96 | T55: 830.44 | U55: 48794.53 | V55: 9888 | X55: 655.5 | AD55: =SUM(J55:AC55) -> 143180.43 | AE55: =AD55-SUM(J55:AC55) -> 0 | AF55: =AD55-I55 -> 0 | AG55: =ROUND(H55,2) -> 142.86 | AH55: =ROUND(AG55*0.07,2) -> 10 | AI55: =ROUND(AG55*0.03,2) -> 4.29 | AJ55: =ROUND(AG55*0.02,2) -> 2.86 | AK55: =IF(AR55,Y55/(AR55*1.12)*AR55,0) -> 0 | AL55: =ROUND(Y55-AK55,2) -> 0 | AM55: =ROUND(AG55-AK55,2) -> 142.86 | AN55: =ROUND(AM55*0.07,2) -> 10 | AO55: =ROUND(AM55*0.03,2) -> 4.29 | AP55: =ROUND(AH55+AI55+AJ55-AL55-AN55-AO55,2) -> 2.86 | AQ55: ="TJ"&A55 -> TJ202512041519000546618 | AR55: =IF(E55="无全额",0,MID(E55,4,2)*1) -> 0.05
A56: 202512041540000452960 | B56: 平云小匠 | C56: 技术服务 | D56: 小时间承揽 | E56: 专票（6%） | F56: =ROUND(SUMIF([1]开票!$A$2:$A$1750,[1]申请!AQ56,[1]开票!$C$2:$C$1750),2) -> 449645 | G56: =ROUND(SUMIF([1]开票!$A$2:$A$1750,[1]申请!AQ56,[1]开票!$D$2:$D$1750),2) -> 0 | H56: =ROUND(SUMIF([1]开票!$A$2:$A$1750,[1]申请!AQ56,[1]开票!$E$2:$E$1750),2) -> 26978.7 | I56: =SUM(F56:H56) -> 476623.7 | Q56: 23878.7 | Z56: 452745 | AD56: =SUM(J56:AC56) -> 476623.7 | AE56: =AD56-SUM(J56:AC56) -> 0 | AF56: =AD56-I56 -> 0 | AG56: =ROUND(H56,2) -> 26978.7 | AH56: =ROUND(AG56*0.07,2) -> 1888.51 | AI56: =ROUND(AG56*0.03,2) -> 809.36 | AJ56: =ROUND(AG56*0.02,2) -> 539.57 | AK56: =IF(AR56,Y56/(AR56*1.12)*AR56,0) -> 0 | AL56: =ROUND(Y56-AK56,2) -> 0 | AM56: =ROUND(AG56-AK56,2) -> 26978.7 | AN56: =ROUND(AM56*0.07,2) -> 1888.51 | AO56: =ROUND(AM56*0.03,2) -> 809.36 | AP56: =ROUND(AH56+AI56+AJ56-AL56-AN56-AO56,2) -> 539.57 | AQ56: ="TJ"&A56 -> TJ202512041540000452960 | AR56: =IF(E56="无全额",0,MID(E56,4,2)*1) -> 0.06
A57: 202512041556000507999 | B57: 重庆壹零柒陆益安药房连锁有限责任公司 | C57: 劳务承揽 | D57: 承揽业务 | E57: 专票（5%） | F57: =ROUND(SUMIF([1]开票!$A$2:$A$1750,[1]申请!AQ57,[1]开票!$C$2:$C$1750),2) -> 2357.14 | G57: =ROUND(SUMIF([1]开票!$A$2:$A$1750,[1]申请!AQ57,[1]开票!$D$2:$D$1750),2) -> 7425 | H57: =ROUND(SUMIF([1]开票!$A$2:$A$1750,[1]申请!AQ57,[1]开票!$E$2:$E$1750),2) -> 117.86 | I57: =SUM(F57:H57) -> 9900 | L57: 9900 | AD57: =SUM(J57:AC57) -> 9900 | AE57: =AD57-SUM(J57:AC57) -> 0 | AF57: =AD57-I57 -> 0 | AG57: =ROUND(H57,2) -> 117.86 | AH57: =ROUND(AG57*0.07,2) -> 8.25 | AI57: =ROUND(AG57*0.03,2) -> 3.54 | AJ57: =ROUND(AG57*0.02,2) -> 2.36 | AK57: =IF(AR57,Y57/(AR57*1.12)*AR57,0) -> 0 | AL57: =ROUND(Y57-AK57,2) -> 0 | AM57: =ROUND(AG57-AK57,2) -> 117.86 | AN57: =ROUND(AM57*0.07,2) -> 8.25 | AO57: =ROUND(AM57*0.03,2) -> 3.54 | AP57: =ROUND(AH57+AI57+AJ57-AL57-AN57-AO57,2) -> 2.36 | AQ57: ="TJ"&A57 -> TJ202512041556000507999 | AR57: =IF(E57="无全额",0,MID(E57,4,2)*1) -> 0.05
A58: 202512041626000319451 | B58: 广州水投城服保安服务有限公司 | C58: 劳务承揽 | D58: 承揽业务 | E58: 专票（6%） | F58: =ROUND(SUMIF([1]开票!$A$2:$A$1750,[1]申请!AQ58,[1]开票!$C$2:$C$1750),2) -> 16770.13 | G58: =ROUND(SUMIF([1]开票!$A$2:$A$1750,[1]申请!AQ58,[1]开票!$D$2:$D$1750),2) -> 0 | H58: =ROUND(SUMIF([1]开票!$A$2:$A$1750,[1]申请!AQ58,[1]开票!$E$2:$E$1750),2) -> 1006.21 | I58: =SUM(F58:H58) -> 17776.34 | L58: 17776.34 | AD58: =SUM(J58:AC58) -> 17776.34 | AE58: =AD58-SUM(J58:AC58) -> 0 | AF58: =AD58-I58 -> 0 | AG58: =ROUND(H58,2) -> 1006.21 | AH58: =ROUND(AG58*0.07,2) -> 70.43 | AI58: =ROUND(AG58*0.03,2) -> 30.19 | AJ58: =ROUND(AG58*0.02,2) -> 20.12 | AK58: =IF(AR58,Y58/(AR58*1.12)*AR58,0) -> 0 | AL58: =ROUND(Y58-AK58,2) -> 0 | AM58: =ROUND(AG58-AK58,2) -> 1006.21 | AN58: =ROUND(AM58*0.07,2) -> 70.43 | AO58: =ROUND(AM58*0.03,2) -> 30.19 | AP58: =ROUND(AH58+AI58+AJ58-AL58-AN58-AO58,2) -> 20.12 | AQ58: ="TJ"&A58 -> TJ202512041626000319451 | AR58: =IF(E58="无全额",0,MID(E58,4,2)*1) -> 0.06
A59: 202512041638000199182 | B59: 广东-禹洲星城（半承揽） | C59: 劳务承揽 | D59: 派遣业务 | E59: 专票（6%） | F59: =ROUND(SUMIF([1]开票!$A$2:$A$1750,[1]申请!AQ59,[1]开票!$C$2:$C$1750),2) -> 23501.25 | G59: =ROUND(SUMIF([1]开票!$A$2:$A$1750,[1]申请!AQ59,[1]开票!$D$2:$D$1750),2) -> 0 | H59: =ROUND(SUMIF([1]开票!$A$2:$A$1750,[1]申请!AQ59,[1]开票!$E$2:$E$1750),2) -> 1410.08 | I59: =SUM(F59:H59) -> 24911.33 | J59: 35.4 | S59: 18829.84 | T59: 273.1 | U59: 3560 | V59: 500 | X59: 144.36 | Y59: 1568.63 | AD59: =SUM(J59:AC59) -> 24911.33 | AE59: =AD59-SUM(J59:AC59) -> 0 | AF59: =AD59-I59 -> 0 | AG59: =ROUND(H59,2) -> 1410.08 | AH59: =ROUND(AG59*0.07,2) -> 98.71 | AI59: =ROUND(AG59*0.03,2) -> 42.3 | AJ59: =ROUND(AG59*0.02,2) -> 28.2 | AK59: =IF(AR59,Y59/(AR59*1.12)*AR59,0) -> 1400.5625 | AL59: =ROUND(Y59-AK59,2) -> 168.07 | AM59: =ROUND(AG59-AK59,2) -> 9.52 | AN59: =ROUND(AM59*0.07,2) -> 0.67 | AO59: =ROUND(AM59*0.03,2) -> 0.29 | AP59: =ROUND(AH59+AI59+AJ59-AL59-AN59-AO59,2) -> 0.18 | AQ59: ="TJ"&A59 -> TJ202512041638000199182 | AR59: =IF(E59="无全额",0,MID(E59,4,2)*1) -> 0.06
A60: 202512041649000480465 | B60: 湖南-湖南珠啤(湖南公司) | C60: 劳务承揽 | D60: 承揽业务 | E60: 专票（6%） | F60: =ROUND(SUMIF([1]开票!$A$2:$A$1750,[1]申请!AQ60,[1]开票!$C$2:$C$1750),2) -> 59187.69 | G60: =ROUND(SUMIF([1]开票!$A$2:$A$1750,[1]申请!AQ60,[1]开票!$D$2:$D$1750),2) -> 0 | H60: =ROUND(SUMIF([1]开票!$A$2:$A$1750,[1]申请!AQ60,[1]开票!$E$2:$E$1750),2) -> 3551.26 | I60: =SUM(F60:H60) -> 62738.95 | L60: 62738.95 | AD60: =SUM(J60:AC60) -> 62738.95 | AE60: =AD60-SUM(J60:AC60) -> 0 | AF60: =AD60-I60 -> 0 | AG60: =ROUND(H60,2) -> 3551.26 | AH60: =ROUND(AG60*0.07,2) -> 248.59 | AI60: =ROUND(AG60*0.03,2) -> 106.54 | AJ60: =ROUND(AG60*0.02,2) -> 71.03 | AK60: =IF(AR60,Y60/(AR60*1.12)*AR60,0) -> 0 | AL60: =ROUND(Y60-AK60,2) -> 0 | AM60: =ROUND(AG60-AK60,2) -> 3551.26 | AN60: =ROUND(AM60*0.07,2) -> 248.59 | AO60: =ROUND(AM60*0.03,2) -> 106.54 | AP60: =ROUND(AH60+AI60+AJ60-AL60-AN60-AO60,2) -> 71.03 | AQ60: ="TJ"&A60 -> TJ202512041649000480465 | AR60: =IF(E60="无全额",0,MID(E60,4,2)*1) -> 0.06
A61: 202512041655000002620 | B61: 华润电力（广东）能源服务有限公司 | C61: 劳务派遣 | D61: 派遣业务 | E61: 专票（5%） | F61: =ROUND(SUMIF([1]开票!$A$2:$A$1750,[1]申请!AQ61,[1]开票!$C$2:$C$1750),2) -> 161.9 | G61: =ROUND(SUMIF([1]开票!$A$2:$A$1750,[1]申请!AQ61,[1]开票!$D$2:$D$1750),2) -> 83312.25 | H61: =ROUND(SUMIF([1]开票!$A$2:$A$1750,[1]申请!AQ61,[1]开票!$E$2:$E$1750),2) -> 8.1 | I61: =SUM(F61:H61) -> 83482.25 | J61: 170 | S61: 64480.42 | T61: 531.1 | U61: 13980.73 | V61: 4320 | W61: 0 | AD61: =SUM(J61:AC61) -> 83482.25 | AE61: =AD61-SUM(J61:AC61) -> 0 | AF61: =AD61-I61 -> 0 | AG61: =ROUND(H61,2) -> 8.1 | AH61: =ROUND(AG61*0.07,2) -> 0.57 | AI61: =ROUND(AG61*0.03,2) -> 0.24 | AJ61: =ROUND(AG61*0.02,2) -> 0.16 | AK61: =IF(AR61,Y61/(AR61*1.12)*AR61,0) -> 0 | AL61: =ROUND(Y61-AK61,2) -> 0 | AM61: =ROUND(AG61-AK61,2) -> 8.1 | AN61: =ROUND(AM61*0.07,2) -> 0.57 | AO61: =ROUND(AM61*0.03,2) -> 0.24 | AP61: =ROUND(AH61+AI61+AJ61-AL61-AN61-AO61,2) -> 0.16 | AQ61: ="TJ"&A61 -> TJ202512041655000002620 | AR61: =IF(E61="无全额",0,MID(E61,4,2)*1) -> 0.05
A62: 202512041718000052225 | B62: 希音-试衣模特 | C62: 劳务派遣 | D62: 派遣业务 | E62: 专票（5%） | F62: =ROUND(SUMIF([1]开票!$A$2:$A$1750,[1]申请!AQ62,[1]开票!$C$2:$C$1750),2) -> 6621.1 | G62: =ROUND(SUMIF([1]开票!$A$2:$A$1750,[1]申请!AQ62,[1]开票!$D$2:$D$1750),2) -> 82763.76 | H62: =ROUND(SUMIF([1]开票!$A$2:$A$1750,[1]申请!AQ62,[1]开票!$E$2:$E$1750),2) -> 331.05 | I62: =SUM(F62:H62) -> 89715.91 | J62: 6621.11 | S62: 82067.77 | T62: 695.99 | Y62: 331.04 | AD62: =SUM(J62:AC62) -> 89715.91 | AE62: =AD62-SUM(J62:AC62) -> 0 | AF62: =AD62-I62 -> 0 | AG62: =ROUND(H62,2) -> 331.05 | AH62: =ROUND(AG62*0.07,2) -> 23.17 | AI62: =ROUND(AG62*0.03,2) -> 9.93 | AJ62: =ROUND(AG62*0.02,2) -> 6.62 | AK62: =IF(AR62,Y62/(AR62*1.12)*AR62,0) -> 295.57143 | AL62: =ROUND(Y62-AK62,2) -> 35.47 | AM62: =ROUND(AG62-AK62,2) -> 35.48 | AN62: =ROUND(AM62*0.07,2) -> 2.48 | AO62: =ROUND(AM62*0.03,2) -> 1.06 | AP62: =ROUND(AH62+AI62+AJ62-AL62-AN62-AO62,2) -> 0.71 | AQ62: ="TJ"&A62 -> TJ202512041718000052225 | AR62: =IF(E62="无全额",0,MID(E62,4,2)*1) -> 0.05
A63: 202512041924000389047 | B63: 杭州诚云科技有限公司 | C63: 人力资源外包（代理） | D63: 代理业务 | E63: 专票（5%） | F63: =ROUND(SUMIF([1]开票!$A$2:$A$1750,[1]申请!AQ63,[1]开票!$C$2:$C$1750),2) -> 56601.9 | G63: =ROUND(SUMIF([1]开票!$A$2:$A$1750,[1]申请!AQ63,[1]开票!$D$2:$D$1750),2) -> 542853.5 | H63: =ROUND(SUMIF([1]开票!$A$2:$A$1750,[1]申请!AQ63,[1]开票!$E$2:$E$1750),2) -> 2830.1 | I63: =SUM(F63:H63) -> 602285.5 | K63: 59432 | U63: 316219.5 | V63: 226634 | AD63: =SUM(J63:AC63) -> 602285.5 | AE63: =AD63-SUM(J63:AC63) -> 0 | AF63: =AD63-I63 -> 0 | AG63: =ROUND(H63,2) -> 2830.1 | AH63: =ROUND(AG63*0.07,2) -> 198.11 | AI63: =ROUND(AG63*0.03,2) -> 84.9 | AJ63: =ROUND(AG63*0.02,2) -> 56.6 | AK63: =IF(AR63,Y63/(AR63*1.12)*AR63,0) -> 0 | AL63: =ROUND(Y63-AK63,2) -> 0 | AM63: =ROUND(AG63-AK63,2) -> 2830.1 | AN63: =ROUND(AM63*0.07,2) -> 198.11 | AO63: =ROUND(AM63*0.03,2) -> 84.9 | AP63: =ROUND(AH63+AI63+AJ63-AL63-AN63-AO63,2) -> 56.6 | AQ63: ="TJ"&A63 -> TJ202512041924000389047 | AR63: =IF(E63="无全额",0,MID(E63,4,2)*1) -> 0.05
A64: 202512051004000014210 | B64: 华润电力（广东）能源服务有限公司 | C64: 劳务派遣 | D64: 派遣业务 | E64: 专票（5%） | F64: =ROUND(SUMIF([1]开票!$A$2:$A$1750,[1]申请!AQ64,[1]开票!$C$2:$C$1750),2) -> 291.43 | G64: =ROUND(SUMIF([1]开票!$A$2:$A$1750,[1]申请!AQ64,[1]开票!$D$2:$D$1750),2) -> 213501.2 | H64: =ROUND(SUMIF([1]开票!$A$2:$A$1750,[1]申请!AQ64,[1]开票!$E$2:$E$1750),2) -> 14.57 | I64: =SUM(F64:H64) -> 213807.2 | J64: 306 | S64: 168031.37 | T64: 6182.54 | U64: 27047.29 | V64: 12240 | W64: 0 | AD64: =SUM(J64:AC64) -> 213807.2 | AE64: =AD64-SUM(J64:AC64) -> 0 | AF64: =AD64-I64 -> 0 | AG64: =ROUND(H64,2) -> 14.57 | AH64: =ROUND(AG64*0.07,2) -> 1.02 | AI64: =ROUND(AG64*0.03,2) -> 0.44 | AJ64: =ROUND(AG64*0.02,2) -> 0.29 | AK64: =IF(AR64,Y64/(AR64*1.12)*AR64,0) -> 0 | AL64: =ROUND(Y64-AK64,2) -> 0 | AM64: =ROUND(AG64-AK64,2) -> 14.57 | AN64: =ROUND(AM64*0.07,2) -> 1.02 | AO64: =ROUND(AM64*0.03,2) -> 0.44 | AP64: =ROUND(AH64+AI64+AJ64-AL64-AN64-AO64,2) -> 0.29 | AQ64: ="TJ"&A64 -> TJ202512051004000014210 | AR64: =IF(E64="无全额",0,MID(E64,4,2)*1) -> 0.05
A65: 202512051207000131422 | B65: 蚂蚁HRO | C65: 劳务承揽 | D65: 承揽业务 | E65: 专票（6%） | F65: =ROUND(SUMIF([1]开票!$A$2:$A$1750,[1]申请!AQ65,[1]开票!$C$2:$C$1750),2) -> 109901.91 | G65: =ROUND(SUMIF([1]开票!$A$2:$A$1750,[1]申请!AQ65,[1]开票!$D$2:$D$1750),2) -> 0 | H65: =ROUND(SUMIF([1]开票!$A$2:$A$1750,[1]申请!AQ65,[1]开票!$E$2:$E$1750),2) -> 6594.11 | I65: =SUM(F65:H65) -> 116496.02 | J65: 116496.02 | AD65: =SUM(J65:AC65) -> 116496.02 | AE65: =AD65-SUM(J65:AC65) -> 0 | AF65: =AD65-I65 -> 0 | AG65: =ROUND(H65,2) -> 6594.11 | AH65: =ROUND(AG65*0.07,2) -> 461.59 | AI65: =ROUND(AG65*0.03,2) -> 197.82 | AJ65: =ROUND(AG65*0.02,2) -> 131.88 | AK65: =IF(AR65,Y65/(AR65*1.12)*AR65,0) -> 0 | AL65: =ROUND(Y65-AK65,2) -> 0 | AM65: =ROUND(AG65-AK65,2) -> 6594.11 | AN65: =ROUND(AM65*0.07,2) -> 461.59 | AO65: =ROUND(AM65*0.03,2) -> 197.82 | AP65: =ROUND(AH65+AI65+AJ65-AL65-AN65-AO65,2) -> 131.88 | AQ65: ="TJ"&A65 -> TJ202512051207000131422 | AR65: =IF(E65="无全额",0,MID(E65,4,2)*1) -> 0.06
A66: 202512051341000185756 | B66: 广东-北明数科（派遣：行政司机） | C66: 劳务派遣 | D66: 派遣业务 | E66: 专票（5%） | F66: =ROUND(SUMIF([1]开票!$A$2:$A$1750,[1]申请!AQ66,[1]开票!$C$2:$C$1750),2) -> 47.62 | G66: =ROUND(SUMIF([1]开票!$A$2:$A$1750,[1]申请!AQ66,[1]开票!$D$2:$D$1750),2) -> 10070.39 | H66: =ROUND(SUMIF([1]开票!$A$2:$A$1750,[1]申请!AQ66,[1]开票!$E$2:$E$1750),2) -> 2.38 | I66: =SUM(F66:H66) -> 10120.39 | J66: 50 | S66: 7863.52 | T66: 88.56 | U66: 1822.95 | V66: 250 | X66: 45.36 | AD66: =SUM(J66:AC66) -> 10120.39 | AE66: =AD66-SUM(J66:AC66) -> 0 | AF66: =AD66-I66 -> 0 | AG66: =ROUND(H66,2) -> 2.38 | AH66: =ROUND(AG66*0.07,2) -> 0.17 | AI66: =ROUND(AG66*0.03,2) -> 0.07 | AJ66: =ROUND(AG66*0.02,2) -> 0.05 | AK66: =IF(AR66,Y66/(AR66*1.12)*AR66,0) -> 0 | AL66: =ROUND(Y66-AK66,2) -> 0 | AM66: =ROUND(AG66-AK66,2) -> 2.38 | AN66: =ROUND(AM66*0.07,2) -> 0.17 | AO66: =ROUND(AM66*0.03,2) -> 0.07 | AP66: =ROUND(AH66+AI66+AJ66-AL66-AN66-AO66,2) -> 0.05 | AQ66: ="TJ"&A66 -> TJ202512051341000185756 | AR66: =IF(E66="无全额",0,MID(E66,4,2)*1) -> 0.05
A67: 202512051343000577561 | B67: 广东-王老吉(广东公司) | C67: 劳务承揽 | D67: 承揽业务 | E67: 专票（6%） | F67: =ROUND(SUMIF([1]开票!$A$2:$A$1750,[1]申请!AQ67,[1]开票!$C$2:$C$1750),2) -> 118355.66 | G67: =ROUND(SUMIF([1]开票!$A$2:$A$1750,[1]申请!AQ67,[1]开票!$D$2:$D$1750),2) -> 0 | H67: =ROUND(SUMIF([1]开票!$A$2:$A$1750,[1]申请!AQ67,[1]开票!$E$2:$E$1750),2) -> 7101.34 | I67: =SUM(F67:H67) -> 125457 | L67: 125457 | AD67: =SUM(J67:AC67) -> 125457 | AE67: =AD67-SUM(J67:AC67) -> 0 | AF67: =AD67-I67 -> 0 | AG67: =ROUND(H67,2) -> 7101.34 | AH67: =ROUND(AG67*0.07,2) -> 497.09 | AI67: =ROUND(AG67*0.03,2) -> 213.04 | AJ67: =ROUND(AG67*0.02,2) -> 142.03 | AK67: =IF(AR67,Y67/(AR67*1.12)*AR67,0) -> 0 | AL67: =ROUND(Y67-AK67,2) -> 0 | AM67: =ROUND(AG67-AK67,2) -> 7101.34 | AN67: =ROUND(AM67*0.07,2) -> 497.09 | AO67: =ROUND(AM67*0.03,2) -> 213.04 | AP67: =ROUND(AH67+AI67+AJ67-AL67-AN67-AO67,2) -> 142.03 | AQ67: ="TJ"&A67 -> TJ202512051343000577561 | AR67: =IF(E67="无全额",0,MID(E67,4,2)*1) -> 0.06
A68: 202512051345000256626 | B68: 广东-天心制药(广东公司) | C68: 劳务承揽 | D68: 承揽业务 | E68: 专票（6%） | F68: =ROUND(SUMIF([1]开票!$A$2:$A$1750,[1]申请!AQ68,[1]开票!$C$2:$C$1750),2) -> 29609.2 | G68: =ROUND(SUMIF([1]开票!$A$2:$A$1750,[1]申请!AQ68,[1]开票!$D$2:$D$1750),2) -> 0 | H68: =ROUND(SUMIF([1]开票!$A$2:$A$1750,[1]申请!AQ68,[1]开票!$E$2:$E$1750),2) -> 1776.55 | I68: =SUM(F68:H68) -> 31385.75 | L68: 31385.75 | AD68: =SUM(J68:AC68) -> 31385.75 | AE68: =AD68-SUM(J68:AC68) -> 0 | AF68: =AD68-I68 -> 0 | AG68: =ROUND(H68,2) -> 1776.55 | AH68: =ROUND(AG68*0.07,2) -> 124.36 | AI68: =ROUND(AG68*0.03,2) -> 53.3 | AJ68: =ROUND(AG68*0.02,2) -> 35.53 | AK68: =IF(AR68,Y68/(AR68*1.12)*AR68,0) -> 0 | AL68: =ROUND(Y68-AK68,2) -> 0 | AM68: =ROUND(AG68-AK68,2) -> 1776.55 | AN68: =ROUND(AM68*0.07,2) -> 124.36 | AO68: =ROUND(AM68*0.03,2) -> 53.3 | AP68: =ROUND(AH68+AI68+AJ68-AL68-AN68-AO68,2) -> 35.53 | AQ68: ="TJ"&A68 -> TJ202512051345000256626 | AR68: =IF(E68="无全额",0,MID(E68,4,2)*1) -> 0.06
A69: 202512051429000356828 | B69: 软通动力信息技术（集团）股份有限公司 | C69: 劳务承揽 | D69: 小时间承揽 | E69: 专票（6%） | F69: =ROUND(SUMIF([1]开票!$A$2:$A$1750,[1]申请!AQ69,[1]开票!$C$2:$C$1750),2) -> 19683.96 | G69: =ROUND(SUMIF([1]开票!$A$2:$A$1750,[1]申请!AQ69,[1]开票!$D$2:$D$1750),2) -> 0 | H69: =ROUND(SUMIF([1]开票!$A$2:$A$1750,[1]申请!AQ69,[1]开票!$E$2:$E$1750),2) -> 1181.04 | I69: =SUM(F69:H69) -> 20865 | Q69: 1365 | Z69: 19500 | AD69: =SUM(J69:AC69) -> 20865 | AE69: =AD69-SUM(J69:AC69) -> 0 | AF69: =AD69-I69 -> 0 | AG69: =ROUND(H69,2) -> 1181.04 | AH69: =ROUND(AG69*0.07,2) -> 82.67 | AI69: =ROUND(AG69*0.03,2) -> 35.43 | AJ69: =ROUND(AG69*0.02,2) -> 23.62 | AK69: =IF(AR69,Y69/(AR69*1.12)*AR69,0) -> 0 | AL69: =ROUND(Y69-AK69,2) -> 0 | AM69: =ROUND(AG69-AK69,2) -> 1181.04 | AN69: =ROUND(AM69*0.07,2) -> 82.67 | AO69: =ROUND(AM69*0.03,2) -> 35.43 | AP69: =ROUND(AH69+AI69+AJ69-AL69-AN69-AO69,2) -> 23.62 | AQ69: ="TJ"&A69 -> TJ202512051429000356828 | AR69: =IF(E69="无全额",0,MID(E69,4,2)*1) -> 0.06
A70: 202512051434000156643 | B70: 软通动力信息技术（集团）股份有限公司 | C70: 劳务承揽 | D70: 小时间承揽 | E70: 专票（6%） | F70: =ROUND(SUMIF([1]开票!$A$2:$A$1750,[1]申请!AQ70,[1]开票!$C$2:$C$1750),2) -> 19683.96 | G70: =ROUND(SUMIF([1]开票!$A$2:$A$1750,[1]申请!AQ70,[1]开票!$D$2:$D$1750),2) -> 0 | H70: =ROUND(SUMIF([1]开票!$A$2:$A$1750,[1]申请!AQ70,[1]开票!$E$2:$E$1750),2) -> 1181.04 | I70: =SUM(F70:H70) -> 20865 | Q70: 1365 | Z70: 19500 | AD70: =SUM(J70:AC70) -> 20865 | AE70: =AD70-SUM(J70:AC70) -> 0 | AF70: =AD70-I70 -> 0 | AG70: =ROUND(H70,2) -> 1181.04 | AH70: =ROUND(AG70*0.07,2) -> 82.67 | AI70: =ROUND(AG70*0.03,2) -> 35.43 | AJ70: =ROUND(AG70*0.02,2) -> 23.62 | AK70: =IF(AR70,Y70/(AR70*1.12)*AR70,0) -> 0 | AL70: =ROUND(Y70-AK70,2) -> 0 | AM70: =ROUND(AG70-AK70,2) -> 1181.04 | AN70: =ROUND(AM70*0.07,2) -> 82.67 | AO70: =ROUND(AM70*0.03,2) -> 35.43 | AP70: =ROUND(AH70+AI70+AJ70-AL70-AN70-AO70,2) -> 23.62 | AQ70: ="TJ"&A70 -> TJ202512051434000156643 | AR70: =IF(E70="无全额",0,MID(E70,4,2)*1) -> 0.06
A71: 202512051434000235037 | B71: 华润电力（广东）能源服务有限公司 | C71: 劳务派遣 | D71: 派遣业务 | E71: 专票（5%） | F71: =ROUND(SUMIF([1]开票!$A$2:$A$1750,[1]申请!AQ71,[1]开票!$C$2:$C$1750),2) -> 3740 | G71: =ROUND(SUMIF([1]开票!$A$2:$A$1750,[1]申请!AQ71,[1]开票!$D$2:$D$1750),2) -> 2109364 | H71: =ROUND(SUMIF([1]开票!$A$2:$A$1750,[1]申请!AQ71,[1]开票!$E$2:$E$1750),2) -> 187 | I71: =SUM(F71:H71) -> 2113291 | J71: 3927 | S71: 1584539.9 | T71: 26118.89 | U71: 336195.22 | V71: 162510 | W71: 0 | AD71: =SUM(J71:AC71) -> 2113291 | AE71: =AD71-SUM(J71:AC71) -> 0 | AF71: =AD71-I71 -> 0 | AG71: =ROUND(H71,2) -> 187 | AH71: =ROUND(AG71*0.07,2) -> 13.09 | AI71: =ROUND(AG71*0.03,2) -> 5.61 | AJ71: =ROUND(AG71*0.02,2) -> 3.74 | AK71: =IF(AR71,Y71/(AR71*1.12)*AR71,0) -> 0 | AL71: =ROUND(Y71-AK71,2) -> 0 | AM71: =ROUND(AG71-AK71,2) -> 187 | AN71: =ROUND(AM71*0.07,2) -> 13.09 | AO71: =ROUND(AM71*0.03,2) -> 5.61 | AP71: =ROUND(AH71+AI71+AJ71-AL71-AN71-AO71,2) -> 3.74 | AQ71: ="TJ"&A71 -> TJ202512051434000235037 | AR71: =IF(E71="无全额",0,MID(E71,4,2)*1) -> 0.05
A72: 202512051436000061048 | B72: 软通动力信息技术（集团）股份有限公司 | C72: 劳务承揽 | D72: 小时间承揽 | E72: 专票（6%） | F72: =ROUND(SUMIF([1]开票!$A$2:$A$1750,[1]申请!AQ72,[1]开票!$C$2:$C$1750),2) -> 19683.96 | G72: =ROUND(SUMIF([1]开票!$A$2:$A$1750,[1]申请!AQ72,[1]开票!$D$2:$D$1750),2) -> 0 | H72: =ROUND(SUMIF([1]开票!$A$2:$A$1750,[1]申请!AQ72,[1]开票!$E$2:$E$1750),2) -> 1181.04 | I72: =SUM(F72:H72) -> 20865 | Q72: 1365 | Z72: 19500 | AD72: =SUM(J72:AC72) -> 20865 | AE72: =AD72-SUM(J72:AC72) -> 0 | AF72: =AD72-I72 -> 0 | AG72: =ROUND(H72,2) -> 1181.04 | AH72: =ROUND(AG72*0.07,2) -> 82.67 | AI72: =ROUND(AG72*0.03,2) -> 35.43 | AJ72: =ROUND(AG72*0.02,2) -> 23.62 | AK72: =IF(AR72,Y72/(AR72*1.12)*AR72,0) -> 0 | AL72: =ROUND(Y72-AK72,2) -> 0 | AM72: =ROUND(AG72-AK72,2) -> 1181.04 | AN72: =ROUND(AM72*0.07,2) -> 82.67 | AO72: =ROUND(AM72*0.03,2) -> 35.43 | AP72: =ROUND(AH72+AI72+AJ72-AL72-AN72-AO72,2) -> 23.62 | AQ72: ="TJ"&A72 -> TJ202512051436000061048 | AR72: =IF(E72="无全额",0,MID(E72,4,2)*1) -> 0.06
A73: 202512051520000077707 | B73: 广东-河北珠啤(广东公司) | C73: 劳务承揽 | D73: 承揽业务 | E73: 专票（6%） | F73: =ROUND(SUMIF([1]开票!$A$2:$A$1750,[1]申请!AQ73,[1]开票!$C$2:$C$1750),2) -> 4649.28 | G73: =ROUND(SUMIF([1]开票!$A$2:$A$1750,[1]申请!AQ73,[1]开票!$D$2:$D$1750),2) -> 0 | H73: =ROUND(SUMIF([1]开票!$A$2:$A$1750,[1]申请!AQ73,[1]开票!$E$2:$E$1750),2) -> 278.96 | I73: =SUM(F73:H73) -> 4928.24 | L73: 4928.24 | AD73: =SUM(J73:AC73) -> 4928.24 | AE73: =AD73-SUM(J73:AC73) -> 0 | AF73: =AD73-I73 -> 0 | AG73: =ROUND(H73,2) -> 278.96 | AH73: =ROUND(AG73*0.07,2) -> 19.53 | AI73: =ROUND(AG73*0.03,2) -> 8.37 | AJ73: =ROUND(AG73*0.02,2) -> 5.58 | AK73: =IF(AR73,Y73/(AR73*1.12)*AR73,0) -> 0 | AL73: =ROUND(Y73-AK73,2) -> 0 | AM73: =ROUND(AG73-AK73,2) -> 278.96 | AN73: =ROUND(AM73*0.07,2) -> 19.53 | AO73: =ROUND(AM73*0.03,2) -> 8.37 | AP73: =ROUND(AH73+AI73+AJ73-AL73-AN73-AO73,2) -> 5.58 | AQ73: ="TJ"&A73 -> TJ202512051520000077707 | AR73: =IF(E73="无全额",0,MID(E73,4,2)*1) -> 0.06
A74: 202512051528000021505 | B74: 广州越秀生鲜食品有限公司 | C74: 劳务承揽 | D74: 派遣业务 | E74: 专票（6%） | F74: =ROUND(SUMIF([1]开票!$A$2:$A$1750,[1]申请!AQ74,[1]开票!$C$2:$C$1750),2) -> 63408.75 | G74: =ROUND(SUMIF([1]开票!$A$2:$A$1750,[1]申请!AQ74,[1]开票!$D$2:$D$1750),2) -> 0 | H74: =ROUND(SUMIF([1]开票!$A$2:$A$1750,[1]申请!AQ74,[1]开票!$E$2:$E$1750),2) -> 3804.53 | I74: =SUM(F74:H74) -> 67213.28 | J74: 160 | S74: 53336.74 | T74: 179.38 | U74: 9029.98 | W74: 94 | X74: 190.92 | Y74: 4222.26 | AD74: =SUM(J74:AC74) -> 67213.28 | AE74: =AD74-SUM(J74:AC74) -> 0 | AF74: =AD74-I74 -> 0 | AG74: =ROUND(H74,2) -> 3804.53 | AH74: =ROUND(AG74*0.07,2) -> 266.32 | AI74: =ROUND(AG74*0.03,2) -> 114.14 | AJ74: =ROUND(AG74*0.02,2) -> 76.09 | AK74: =IF(AR74,Y74/(AR74*1.12)*AR74,0) -> 3769.875 | AL74: =ROUND(Y74-AK74,2) -> 452.39 | AM74: =ROUND(AG74-AK74,2) -> 34.66 | AN74: =ROUND(AM74*0.07,2) -> 2.43 | AO74: =ROUND(AM74*0.03,2) -> 1.04 | AP74: =ROUND(AH74+AI74+AJ74-AL74-AN74-AO74,2) -> 0.69 | AQ74: ="TJ"&A74 -> TJ202512051528000021505 | AR74: =IF(E74="无全额",0,MID(E74,4,2)*1) -> 0.06
A75: 202512051533000152147 | B75: 广州汽车集团股份有限公司 | C75: 劳务承揽 | D75: 承揽业务 | E75: 专票（6%） | F75: =ROUND(SUMIF([1]开票!$A$2:$A$1750,[1]申请!AQ75,[1]开票!$C$2:$C$1750),2) -> 58239.91 | G75: =ROUND(SUMIF([1]开票!$A$2:$A$1750,[1]申请!AQ75,[1]开票!$D$2:$D$1750),2) -> 0 | H75: =ROUND(SUMIF([1]开票!$A$2:$A$1750,[1]申请!AQ75,[1]开票!$E$2:$E$1750),2) -> 3494.39 | I75: =SUM(F75:H75) -> 61734.3 | L75: 61734.3 | AD75: =SUM(J75:AC75) -> 61734.3 | AE75: =AD75-SUM(J75:AC75) -> 0 | AF75: =AD75-I75 -> 0 | AG75: =ROUND(H75,2) -> 3494.39 | AH75: =ROUND(AG75*0.07,2) -> 244.61 | AI75: =ROUND(AG75*0.03,2) -> 104.83 | AJ75: =ROUND(AG75*0.02,2) -> 69.89 | AK75: =IF(AR75,Y75/(AR75*1.12)*AR75,0) -> 0 | AL75: =ROUND(Y75-AK75,2) -> 0 | AM75: =ROUND(AG75-AK75,2) -> 3494.39 | AN75: =ROUND(AM75*0.07,2) -> 244.61 | AO75: =ROUND(AM75*0.03,2) -> 104.83 | AP75: =ROUND(AH75+AI75+AJ75-AL75-AN75-AO75,2) -> 69.89 | AQ75: ="TJ"&A75 -> TJ202512051533000152147 | AR75: =IF(E75="无全额",0,MID(E75,4,2)*1) -> 0.06
A76: 202512051546000108257 | B76: 广东-国际香料(广东公司) | C76: 劳务承揽 | D76: 派遣业务 | E76: 专票（6%） | F76: =ROUND(SUMIF([1]开票!$A$2:$A$1750,[1]申请!AQ76,[1]开票!$C$2:$C$1750),2) -> 10752.52 | G76: =ROUND(SUMIF([1]开票!$A$2:$A$1750,[1]申请!AQ76,[1]开票!$D$2:$D$1750),2) -> 0 | H76: =ROUND(SUMIF([1]开票!$A$2:$A$1750,[1]申请!AQ76,[1]开票!$E$2:$E$1750),2) -> 645.15 | I76: =SUM(F76:H76) -> 11397.67 | L76: 995.37 | S76: 5685.63 | T76: 0 | U76: 2562.69 | V76: 1252 | W76: 40 | X76: 144.29 | Y76: 717.69 | AD76: =SUM(J76:AC76) -> 11397.67 | AE76: =AD76-SUM(J76:AC76) -> 0 | AF76: =AD76-I76 -> 0 | AG76: =ROUND(H76,2) -> 645.15 | AH76: =ROUND(AG76*0.07,2) -> 45.16 | AI76: =ROUND(AG76*0.03,2) -> 19.35 | AJ76: =ROUND(AG76*0.02,2) -> 12.9 | AK76: =IF(AR76,Y76/(AR76*1.12)*AR76,0) -> 640.79464 | AL76: =ROUND(Y76-AK76,2) -> 76.9 | AM76: =ROUND(AG76-AK76,2) -> 4.36 | AN76: =ROUND(AM76*0.07,2) -> 0.31 | AO76: =ROUND(AM76*0.03,2) -> 0.13 | AP76: =ROUND(AH76+AI76+AJ76-AL76-AN76-AO76,2) -> 0.07 | AQ76: ="TJ"&A76 -> TJ202512051546000108257 | AR76: =IF(E76="无全额",0,MID(E76,4,2)*1) -> 0.06
A77: 202512051638000450827 | B77: 河北珠江啤酒有限公司-促销 | C77: 劳务派遣 | D77: 承揽业务 | E77: 专票（6%） | F77: =ROUND(SUMIF([1]开票!$A$2:$A$1750,[1]申请!AQ77,[1]开票!$C$2:$C$1750),2) -> 6201.34 | G77: =ROUND(SUMIF([1]开票!$A$2:$A$1750,[1]申请!AQ77,[1]开票!$D$2:$D$1750),2) -> 0 | H77: =ROUND(SUMIF([1]开票!$A$2:$A$1750,[1]申请!AQ77,[1]开票!$E$2:$E$1750),2) -> 372.08 | I77: =SUM(F77:H77) -> 6573.42 | J77: 145 | S77: 5694.16 | U77: 330.6 | Y77: 403.66 | AD77: =SUM(J77:AC77) -> 6573.42 | AE77: =AD77-SUM(J77:AC77) -> 0 | AF77: =AD77-I77 -> 0 | AG77: =ROUND(H77,2) -> 372.08 | AH77: =ROUND(AG77*0.07,2) -> 26.05 | AI77: =ROUND(AG77*0.03,2) -> 11.16 | AJ77: =ROUND(AG77*0.02,2) -> 7.44 | AK77: =IF(AR77,Y77/(AR77*1.12)*AR77,0) -> 360.41071 | AL77: =ROUND(Y77-AK77,2) -> 43.25 | AM77: =ROUND(AG77-AK77,2) -> 11.67 | AN77: =ROUND(AM77*0.07,2) -> 0.82 | AO77: =ROUND(AM77*0.03,2) -> 0.35 | AP77: =ROUND(AH77+AI77+AJ77-AL77-AN77-AO77,2) -> 0.23 | AQ77: ="TJ"&A77 -> TJ202512051638000450827 | AR77: =IF(E77="无全额",0,MID(E77,4,2)*1) -> 0.06
A78: 202512051705000129633 | B78: 蚂蚁金服-直管 | C78: 劳务承揽 | D78: 承揽业务 | E78: 专票（6%） | F78: =ROUND(SUMIF([1]开票!$A$2:$A$1750,[1]申请!AQ78,[1]开票!$C$2:$C$1750),2) -> 44372.19 | G78: =ROUND(SUMIF([1]开票!$A$2:$A$1750,[1]申请!AQ78,[1]开票!$D$2:$D$1750),2) -> 0 | H78: =ROUND(SUMIF([1]开票!$A$2:$A$1750,[1]申请!AQ78,[1]开票!$E$2:$E$1750),2) -> 2662.33 | I78: =SUM(F78:H78) -> 47034.52 | J78: 466.24 | S78: 34285.24 | T78: 843.36 | U78: 6537.52 | V78: 1780.48 | W78: 160 | Y78: 2961.68 | AA78: 0 | AD78: =SUM(J78:AC78) -> 47034.52 | AE78: =AD78-SUM(J78:AC78) -> 0 | AF78: =AD78-I78 -> 0 | AG78: =ROUND(H78,2) -> 2662.33 | AH78: =ROUND(AG78*0.07,2) -> 186.36 | AI78: =ROUND(AG78*0.03,2) -> 79.87 | AJ78: =ROUND(AG78*0.02,2) -> 53.25 | AK78: =IF(AR78,Y78/(AR78*1.12)*AR78,0) -> 2644.3571 | AL78: =ROUND(Y78-AK78,2) -> 317.32 | AM78: =ROUND(AG78-AK78,2) -> 17.97 | AN78: =ROUND(AM78*0.07,2) -> 1.26 | AO78: =ROUND(AM78*0.03,2) -> 0.54 | AP78: =ROUND(AH78+AI78+AJ78-AL78-AN78-AO78,2) -> 0.36 | AQ78: ="TJ"&A78 -> TJ202512051705000129633 | AR78: =IF(E78="无全额",0,MID(E78,4,2)*1) -> 0.06
A79: 202512062035000130046 | B79: 广州王老吉药业股份有限公司-促销 | C79: 劳务承揽 | D79: 派遣业务 | E79: 专票（6%） | F79: =ROUND(SUMIF([1]开票!$A$2:$A$1750,[1]申请!AQ79,[1]开票!$C$2:$C$1750),2) -> 479625.24 | G79: =ROUND(SUMIF([1]开票!$A$2:$A$1750,[1]申请!AQ79,[1]开票!$D$2:$D$1750),2) -> 0 | H79: =ROUND(SUMIF([1]开票!$A$2:$A$1750,[1]申请!AQ79,[1]开票!$E$2:$E$1750),2) -> 28777.53 | I79: =SUM(F79:H79) -> 508402.77 | J79: 29680.77 | S79: 478722 | AD79: =SUM(J79:AC79) -> 508402.77 | AE79: =AD79-SUM(J79:AC79) -> 0 | AF79: =AD79-I79 -> 0 | AG79: =ROUND(H79,2) -> 28777.53 | AH79: =ROUND(AG79*0.07,2) -> 2014.43 | AI79: =ROUND(AG79*0.03,2) -> 863.33 | AJ79: =ROUND(AG79*0.02,2) -> 575.55 | AK79: =IF(AR79,Y79/(AR79*1.12)*AR79,0) -> 0 | AL79: =ROUND(Y79-AK79,2) -> 0 | AM79: =ROUND(AG79-AK79,2) -> 28777.53 | AN79: =ROUND(AM79*0.07,2) -> 2014.43 | AO79: =ROUND(AM79*0.03,2) -> 863.33 | AP79: =ROUND(AH79+AI79+AJ79-AL79-AN79-AO79,2) -> 575.55 | AQ79: ="TJ"&A79 -> TJ202512062035000130046 | AR79: =IF(E79="无全额",0,MID(E79,4,2)*1) -> 0.06
A80: 202512080958000512038 | B80: 广东-金鹰国际货代(广东公司) | C80: 劳务承揽 | D80: 承揽业务 | E80: 专票（6%） | F80: =ROUND(SUMIF([1]开票!$A$2:$A$1750,[1]申请!AQ80,[1]开票!$C$2:$C$1750),2) -> 50488.37 | G80: =ROUND(SUMIF([1]开票!$A$2:$A$1750,[1]申请!AQ80,[1]开票!$D$2:$D$1750),2) -> 0 | H80: =ROUND(SUMIF([1]开票!$A$2:$A$1750,[1]申请!AQ80,[1]开票!$E$2:$E$1750),2) -> 3029.3 | I80: =SUM(F80:H80) -> 53517.67 | L80: 53517.67 | AD80: =SUM(J80:AC80) -> 53517.67 | AE80: =AD80-SUM(J80:AC80) -> 0 | AF80: =AD80-I80 -> 0 | AG80: =ROUND(H80,2) -> 3029.3 | AH80: =ROUND(AG80*0.07,2) -> 212.05 | AI80: =ROUND(AG80*0.03,2) -> 90.88 | AJ80: =ROUND(AG80*0.02,2) -> 60.59 | AK80: =IF(AR80,Y80/(AR80*1.12)*AR80,0) -> 0 | AL80: =ROUND(Y80-AK80,2) -> 0 | AM80: =ROUND(AG80-AK80,2) -> 3029.3 | AN80: =ROUND(AM80*0.07,2) -> 212.05 | AO80: =ROUND(AM80*0.03,2) -> 90.88 | AP80: =ROUND(AH80+AI80+AJ80-AL80-AN80-AO80,2) -> 60.59 | AQ80: ="TJ"&A80 -> TJ202512080958000512038 | AR80: =IF(E80="无全额",0,MID(E80,4,2)*1) -> 0.06
A81: 202512081004000336880 | B81: 广东公司-华南植物园（派遣） | C81: 劳务派遣 | D81: 派遣业务 | E81: 电票（5%） | F81: =ROUND(SUMIF([1]开票!$A$2:$A$1750,[1]申请!AQ81,[1]开票!$C$2:$C$1750),2) -> 309.87 | G81: =ROUND(SUMIF([1]开票!$A$2:$A$1750,[1]申请!AQ81,[1]开票!$D$2:$D$1750),2) -> 6000 | H81: =ROUND(SUMIF([1]开票!$A$2:$A$1750,[1]申请!AQ81,[1]开票!$E$2:$E$1750),2) -> 15.49 | I81: =SUM(F81:H81) -> 6325.36 | J81: 227 | S81: 6000 | W81: 53 | X81: 45.36 | AD81: =SUM(J81:AC81) -> 6325.36 | AE81: =AD81-SUM(J81:AC81) -> 0 | AF81: =AD81-I81 -> 0 | AG81: =ROUND(H81,2) -> 15.49 | AH81: =ROUND(AG81*0.07,2) -> 1.08 | AI81: =ROUND(AG81*0.03,2) -> 0.46 | AJ81: =ROUND(AG81*0.02,2) -> 0.31 | AK81: =IF(AR81,Y81/(AR81*1.12)*AR81,0) -> 0 | AL81: =ROUND(Y81-AK81,2) -> 0 | AM81: =ROUND(AG81-AK81,2) -> 15.49 | AN81: =ROUND(AM81*0.07,2) -> 1.08 | AO81: =ROUND(AM81*0.03,2) -> 0.46 | AP81: =ROUND(AH81+AI81+AJ81-AL81-AN81-AO81,2) -> 0.31 | AQ81: ="TJ"&A81 -> TJ202512081004000336880 | AR81: =IF(E81="无全额",0,MID(E81,4,2)*1) -> 0.05
A82: 202512081040000217346 | B82: 北京图治云安科技有限公司 | C82: 人力资源外包（代理） | D82: 代理业务 | E82: 专票（5%） | F82: =ROUND(SUMIF([1]开票!$A$2:$A$1750,[1]申请!AQ82,[1]开票!$C$2:$C$1750),2) -> 76.19 | G82: =ROUND(SUMIF([1]开票!$A$2:$A$1750,[1]申请!AQ82,[1]开票!$D$2:$D$1750),2) -> 13755.36 | H82: =ROUND(SUMIF([1]开票!$A$2:$A$1750,[1]申请!AQ82,[1]开票!$E$2:$E$1750),2) -> 3.81 | I82: =SUM(F82:H82) -> 13835.36 | K82: 80 | S82: 7677.2 | T82: 82.8 | U82: 3550 | V82: 2400 | X82: 45.36 | AD82: =SUM(J82:AC82) -> 13835.36 | AE82: =AD82-SUM(J82:AC82) -> 0 | AF82: =AD82-I82 -> 0 | AG82: =ROUND(H82,2) -> 3.81 | AH82: =ROUND(AG82*0.07,2) -> 0.27 | AI82: =ROUND(AG82*0.03,2) -> 0.11 | AJ82: =ROUND(AG82*0.02,2) -> 0.08 | AK82: =IF(AR82,Y82/(AR82*1.12)*AR82,0) -> 0 | AL82: =ROUND(Y82-AK82,2) -> 0 | AM82: =ROUND(AG82-AK82,2) -> 3.81 | AN82: =ROUND(AM82*0.07,2) -> 0.27 | AO82: =ROUND(AM82*0.03,2) -> 0.11 | AP82: =ROUND(AH82+AI82+AJ82-AL82-AN82-AO82,2) -> 0.08 | AQ82: ="TJ"&A82 -> TJ202512081040000217346 | AR82: =IF(E82="无全额",0,MID(E82,4,2)*1) -> 0.05
A83: 202512081154000013734 | B83: 广州王老吉药业股份有限公司-促销 | C83: 劳务承揽 | D83: 派遣业务 | E83: 专票（6%） | F83: =ROUND(SUMIF([1]开票!$A$2:$A$1750,[1]申请!AQ83,[1]开票!$C$2:$C$1750),2) -> 11120.94 | G83: =ROUND(SUMIF([1]开票!$A$2:$A$1750,[1]申请!AQ83,[1]开票!$D$2:$D$1750),2) -> 0 | H83: =ROUND(SUMIF([1]开票!$A$2:$A$1750,[1]申请!AQ83,[1]开票!$E$2:$E$1750),2) -> 667.26 | I83: =SUM(F83:H83) -> 11788.2 | J83: 688.2 | S83: 11100 | AD83: =SUM(J83:AC83) -> 11788.2 | AE83: =AD83-SUM(J83:AC83) -> 0 | AF83: =AD83-I83 -> 0 | AG83: =ROUND(H83,2) -> 667.26 | AH83: =ROUND(AG83*0.07,2) -> 46.71 | AI83: =ROUND(AG83*0.03,2) -> 20.02 | AJ83: =ROUND(AG83*0.02,2) -> 13.35 | AK83: =IF(AR83,Y83/(AR83*1.12)*AR83,0) -> 0 | AL83: =ROUND(Y83-AK83,2) -> 0 | AM83: =ROUND(AG83-AK83,2) -> 667.26 | AN83: =ROUND(AM83*0.07,2) -> 46.71 | AO83: =ROUND(AM83*0.03,2) -> 20.02 | AP83: =ROUND(AH83+AI83+AJ83-AL83-AN83-AO83,2) -> 13.35 | AQ83: ="TJ"&A83 -> TJ202512081154000013734 | AR83: =IF(E83="无全额",0,MID(E83,4,2)*1) -> 0.06
A84: 202512081215000092361 | B84: 广东-致美斋（劳务承揽） | C84: 劳务承揽 | D84: 承揽业务 | E84: 专票（6%） | F84: =ROUND(SUMIF([1]开票!$A$2:$A$1750,[1]申请!AQ84,[1]开票!$C$2:$C$1750),2) -> 423.51 | G84: =ROUND(SUMIF([1]开票!$A$2:$A$1750,[1]申请!AQ84,[1]开票!$D$2:$D$1750),2) -> 0 | H84: =ROUND(SUMIF([1]开票!$A$2:$A$1750,[1]申请!AQ84,[1]开票!$E$2:$E$1750),2) -> 25.41 | I84: =SUM(F84:H84) -> 448.92 | L84: 448.92 | AD84: =SUM(J84:AC84) -> 448.92 | AE84: =AD84-SUM(J84:AC84) -> 0 | AF84: =AD84-I84 -> 0 | AG84: =ROUND(H84,2) -> 25.41 | AH84: =ROUND(AG84*0.07,2) -> 1.78 | AI84: =ROUND(AG84*0.03,2) -> 0.76 | AJ84: =ROUND(AG84*0.02,2) -> 0.51 | AK84: =IF(AR84,Y84/(AR84*1.12)*AR84,0) -> 0 | AL84: =ROUND(Y84-AK84,2) -> 0 | AM84: =ROUND(AG84-AK84,2) -> 25.41 | AN84: =ROUND(AM84*0.07,2) -> 1.78 | AO84: =ROUND(AM84*0.03,2) -> 0.76 | AP84: =ROUND(AH84+AI84+AJ84-AL84-AN84-AO84,2) -> 0.51 | AQ84: ="TJ"&A84 -> TJ202512081215000092361 | AR84: =IF(E84="无全额",0,MID(E84,4,2)*1) -> 0.06
A85: 202512081253000131670 | B85: 蚂蚁HRO | C85: 劳务承揽 | D85: 承揽业务 | E85: 专票（6%） | F85: =ROUND(SUMIF([1]开票!$A$2:$A$1750,[1]申请!AQ85,[1]开票!$C$2:$C$1750),2) -> 11957.94 | G85: =ROUND(SUMIF([1]开票!$A$2:$A$1750,[1]申请!AQ85,[1]开票!$D$2:$D$1750),2) -> 0 | H85: =ROUND(SUMIF([1]开票!$A$2:$A$1750,[1]申请!AQ85,[1]开票!$E$2:$E$1750),2) -> 717.48 | I85: =SUM(F85:H85) -> 12675.42 | J85: 12675.42 | AD85: =SUM(J85:AC85) -> 12675.42 | AE85: =AD85-SUM(J85:AC85) -> 0 | AF85: =AD85-I85 -> 0 | AG85: =ROUND(H85,2) -> 717.48 | AH85: =ROUND(AG85*0.07,2) -> 50.22 | AI85: =ROUND(AG85*0.03,2) -> 21.52 | AJ85: =ROUND(AG85*0.02,2) -> 14.35 | AK85: =IF(AR85,Y85/(AR85*1.12)*AR85,0) -> 0 | AL85: =ROUND(Y85-AK85,2) -> 0 | AM85: =ROUND(AG85-AK85,2) -> 717.48 | AN85: =ROUND(AM85*0.07,2) -> 50.22 | AO85: =ROUND(AM85*0.03,2) -> 21.52 | AP85: =ROUND(AH85+AI85+AJ85-AL85-AN85-AO85,2) -> 14.35 | AQ85: ="TJ"&A85 -> TJ202512081253000131670 | AR85: =IF(E85="无全额",0,MID(E85,4,2)*1) -> 0.06
A86: 202512081255000016499 | B86: 蚂蚁HRO | C86: 劳务承揽 | D86: 承揽业务 | E86: 专票（6%） | F86: =ROUND(SUMIF([1]开票!$A$2:$A$1750,[1]申请!AQ86,[1]开票!$C$2:$C$1750),2) -> 21334.82 | G86: =ROUND(SUMIF([1]开票!$A$2:$A$1750,[1]申请!AQ86,[1]开票!$D$2:$D$1750),2) -> 0 | H86: =ROUND(SUMIF([1]开票!$A$2:$A$1750,[1]申请!AQ86,[1]开票!$E$2:$E$1750),2) -> 1280.09 | I86: =SUM(F86:H86) -> 22614.91 | J86: 22614.91 | AD86: =SUM(J86:AC86) -> 22614.91 | AE86: =AD86-SUM(J86:AC86) -> 0 | AF86: =AD86-I86 -> 0 | AG86: =ROUND(H86,2) -> 1280.09 | AH86: =ROUND(AG86*0.07,2) -> 89.61 | AI86: =ROUND(AG86*0.03,2) -> 38.4 | AJ86: =ROUND(AG86*0.02,2) -> 25.6 | AK86: =IF(AR86,Y86/(AR86*1.12)*AR86,0) -> 0 | AL86: =ROUND(Y86-AK86,2) -> 0 | AM86: =ROUND(AG86-AK86,2) -> 1280.09 | AN86: =ROUND(AM86*0.07,2) -> 89.61 | AO86: =ROUND(AM86*0.03,2) -> 38.4 | AP86: =ROUND(AH86+AI86+AJ86-AL86-AN86-AO86,2) -> 25.6 | AQ86: ="TJ"&A86 -> TJ202512081255000016499 | AR86: =IF(E86="无全额",0,MID(E86,4,2)*1) -> 0.06
A87: 202512081258000066546 | B87: 蚂蚁HRO | C87: 劳务承揽 | D87: 承揽业务 | E87: 专票（6%） | F87: =ROUND(SUMIF([1]开票!$A$2:$A$1750,[1]申请!AQ87,[1]开票!$C$2:$C$1750),2) -> 5067.93 | G87: =ROUND(SUMIF([1]开票!$A$2:$A$1750,[1]申请!AQ87,[1]开票!$D$2:$D$1750),2) -> 0 | H87: =ROUND(SUMIF([1]开票!$A$2:$A$1750,[1]申请!AQ87,[1]开票!$E$2:$E$1750),2) -> 304.08 | I87: =SUM(F87:H87) -> 5372.01 | J87: 5372.01 | AD87: =SUM(J87:AC87) -> 5372.01 | AE87: =AD87-SUM(J87:AC87) -> 0 | AF87: =AD87-I87 -> 0 | AG87: =ROUND(H87,2) -> 304.08 | AH87: =ROUND(AG87*0.07,2) -> 21.29 | AI87: =ROUND(AG87*0.03,2) -> 9.12 | AJ87: =ROUND(AG87*0.02,2) -> 6.08 | AK87: =IF(AR87,Y87/(AR87*1.12)*AR87,0) -> 0 | AL87: =ROUND(Y87-AK87,2) -> 0 | AM87: =ROUND(AG87-AK87,2) -> 304.08 | AN87: =ROUND(AM87*0.07,2) -> 21.29 | AO87: =ROUND(AM87*0.03,2) -> 9.12 | AP87: =ROUND(AH87+AI87+AJ87-AL87-AN87-AO87,2) -> 6.08 | AQ87: ="TJ"&A87 -> TJ202512081258000066546 | AR87: =IF(E87="无全额",0,MID(E87,4,2)*1) -> 0.06
A88: 202512081258000548378 | B88: 蚂蚁HRO | C88: 劳务承揽 | D88: 承揽业务 | E88: 专票（6%） | F88: =ROUND(SUMIF([1]开票!$A$2:$A$1750,[1]申请!AQ88,[1]开票!$C$2:$C$1750),2) -> 21394.49 | G88: =ROUND(SUMIF([1]开票!$A$2:$A$1750,[1]申请!AQ88,[1]开票!$D$2:$D$1750),2) -> 0 | H88: =ROUND(SUMIF([1]开票!$A$2:$A$1750,[1]申请!AQ88,[1]开票!$E$2:$E$1750),2) -> 1283.67 | I88: =SUM(F88:H88) -> 22678.16 | J88: 22678.16 | AD88: =SUM(J88:AC88) -> 22678.16 | AE88: =AD88-SUM(J88:AC88) -> 0 | AF88: =AD88-I88 -> 0 | AG88: =ROUND(H88,2) -> 1283.67 | AH88: =ROUND(AG88*0.07,2) -> 89.86 | AI88: =ROUND(AG88*0.03,2) -> 38.51 | AJ88: =ROUND(AG88*0.02,2) -> 25.67 | AK88: =IF(AR88,Y88/(AR88*1.12)*AR88,0) -> 0 | AL88: =ROUND(Y88-AK88,2) -> 0 | AM88: =ROUND(AG88-AK88,2) -> 1283.67 | AN88: =ROUND(AM88*0.07,2) -> 89.86 | AO88: =ROUND(AM88*0.03,2) -> 38.51 | AP88: =ROUND(AH88+AI88+AJ88-AL88-AN88-AO88,2) -> 25.67 | AQ88: ="TJ"&A88 -> TJ202512081258000548378 | AR88: =IF(E88="无全额",0,MID(E88,4,2)*1) -> 0.06
A89: 202512081324000225196 | B89: 广州华德汽车弹簧有限公司 | C89: 劳务承揽 | D89: 承揽业务 | E89: 专票（6%） | F89: =ROUND(SUMIF([1]开票!$A$2:$A$1750,[1]申请!AQ89,[1]开票!$C$2:$C$1750),2) -> 279121.7 | G89: =ROUND(SUMIF([1]开票!$A$2:$A$1750,[1]申请!AQ89,[1]开票!$D$2:$D$1750),2) -> 0 | H89: =ROUND(SUMIF([1]开票!$A$2:$A$1750,[1]申请!AQ89,[1]开票!$E$2:$E$1750),2) -> 16747.3 | I89: =SUM(F89:H89) -> 295869 | L89: 295869 | AD89: =SUM(J89:AC89) -> 295869 | AE89: =AD89-SUM(J89:AC89) -> 0 | AF89: =AD89-I89 -> 0 | AG89: =ROUND(H89,2) -> 16747.3 | AH89: =ROUND(AG89*0.07,2) -> 1172.31 | AI89: =ROUND(AG89*0.03,2) -> 502.42 | AJ89: =ROUND(AG89*0.02,2) -> 334.95 | AK89: =IF(AR89,Y89/(AR89*1.12)*AR89,0) -> 0 | AL89: =ROUND(Y89-AK89,2) -> 0 | AM89: =ROUND(AG89-AK89,2) -> 16747.3 | AN89: =ROUND(AM89*0.07,2) -> 1172.31 | AO89: =ROUND(AM89*0.03,2) -> 502.42 | AP89: =ROUND(AH89+AI89+AJ89-AL89-AN89-AO89,2) -> 334.95 | AQ89: ="TJ"&A89 -> TJ202512081324000225196 | AR89: =IF(E89="无全额",0,MID(E89,4,2)*1) -> 0.06
A90: 202512081331000231105 | B90: 珠海龙源金科铝业有限公司 | C90: 劳务承揽 | D90: 承揽业务 | E90: 专票（6%） | F90: =ROUND(SUMIF([1]开票!$A$2:$A$1750,[1]申请!AQ90,[1]开票!$C$2:$C$1750),2) -> 217781.77 | G90: =ROUND(SUMIF([1]开票!$A$2:$A$1750,[1]申请!AQ90,[1]开票!$D$2:$D$1750),2) -> 0 | H90: =ROUND(SUMIF([1]开票!$A$2:$A$1750,[1]申请!AQ90,[1]开票!$E$2:$E$1750),2) -> 13066.91 | I90: =SUM(F90:H90) -> 230848.68 | L90: 230848.68 | AD90: =SUM(J90:AC90) -> 230848.68 | AE90: =AD90-SUM(J90:AC90) -> 0 | AF90: =AD90-I90 -> 0 | AG90: =ROUND(H90,2) -> 13066.91 | AH90: =ROUND(AG90*0.07,2) -> 914.68 | AI90: =ROUND(AG90*0.03,2) -> 392.01 | AJ90: =ROUND(AG90*0.02,2) -> 261.34 | AK90: =IF(AR90,Y90/(AR90*1.12)*AR90,0) -> 0 | AL90: =ROUND(Y90-AK90,2) -> 0 | AM90: =ROUND(AG90-AK90,2) -> 13066.91 | AN90: =ROUND(AM90*0.07,2) -> 914.68 | AO90: =ROUND(AM90*0.03,2) -> 392.01 | AP90: =ROUND(AH90+AI90+AJ90-AL90-AN90-AO90,2) -> 261.34 | AQ90: ="TJ"&A90 -> TJ202512081331000231105 | AR90: =IF(E90="无全额",0,MID(E90,4,2)*1) -> 0.06
A91: 202512081346000361440 | B91: 广东-致美斋（劳务承揽） | C91: 劳务承揽 | D91: 承揽业务 | E91: 专票（6%） | F91: =ROUND(SUMIF([1]开票!$A$2:$A$1750,[1]申请!AQ91,[1]开票!$C$2:$C$1750),2) -> 1859.01 | G91: =ROUND(SUMIF([1]开票!$A$2:$A$1750,[1]申请!AQ91,[1]开票!$D$2:$D$1750),2) -> 0 | H91: =ROUND(SUMIF([1]开票!$A$2:$A$1750,[1]申请!AQ91,[1]开票!$E$2:$E$1750),2) -> 111.54 | I91: =SUM(F91:H91) -> 1970.55 | L91: 1970.55 | AD91: =SUM(J91:AC91) -> 1970.55 | AE91: =AD91-SUM(J91:AC91) -> 0 | AF91: =AD91-I91 -> 0 | AG91: =ROUND(H91,2) -> 111.54 | AH91: =ROUND(AG91*0.07,2) -> 7.81 | AI91: =ROUND(AG91*0.03,2) -> 3.35 | AJ91: =ROUND(AG91*0.02,2) -> 2.23 | AK91: =IF(AR91,Y91/(AR91*1.12)*AR91,0) -> 0 | AL91: =ROUND(Y91-AK91,2) -> 0 | AM91: =ROUND(AG91-AK91,2) -> 111.54 | AN91: =ROUND(AM91*0.07,2) -> 7.81 | AO91: =ROUND(AM91*0.03,2) -> 3.35 | AP91: =ROUND(AH91+AI91+AJ91-AL91-AN91-AO91,2) -> 2.23 | AQ91: ="TJ"&A91 -> TJ202512081346000361440 | AR91: =IF(E91="无全额",0,MID(E91,4,2)*1) -> 0.06
A92: 202512081404000149666 | B92: 深圳万物商企物业服务有限公司贵阳分公司-首钢 | C92: 劳务承揽 | D92: 承揽业务 | E92: 专票（6%） | F92: =ROUND(SUMIF([1]开票!$A$2:$A$1750,[1]申请!AQ92,[1]开票!$C$2:$C$1750),2) -> 29476.42 | G92: =ROUND(SUMIF([1]开票!$A$2:$A$1750,[1]申请!AQ92,[1]开票!$D$2:$D$1750),2) -> 0 | H92: =ROUND(SUMIF([1]开票!$A$2:$A$1750,[1]申请!AQ92,[1]开票!$E$2:$E$1750),2) -> 1768.59 | I92: =SUM(F92:H92) -> 31245.01 | L92: 31245.01 | AD92: =SUM(J92:AC92) -> 31245.01 | AE92: =AD92-SUM(J92:AC92) -> 0 | AF92: =AD92-I92 -> 0 | AG92: =ROUND(H92,2) -> 1768.59 | AH92: =ROUND(AG92*0.07,2) -> 123.8 | AI92: =ROUND(AG92*0.03,2) -> 53.06 | AJ92: =ROUND(AG92*0.02,2) -> 35.37 | AK92: =IF(AR92,Y92/(AR92*1.12)*AR92,0) -> 0 | AL92: =ROUND(Y92-AK92,2) -> 0 | AM92: =ROUND(AG92-AK92,2) -> 1768.59 | AN92: =ROUND(AM92*0.07,2) -> 123.8 | AO92: =ROUND(AM92*0.03,2) -> 53.06 | AP92: =ROUND(AH92+AI92+AJ92-AL92-AN92-AO92,2) -> 35.37 | AQ92: ="TJ"&A92 -> TJ202512081404000149666 | AR92: =IF(E92="无全额",0,MID(E92,4,2)*1) -> 0.06
A93: 202512081407000571281 | B93: 深圳万物商企物业服务有限公司贵阳分公司 | C93: 劳务承揽 | D93: 承揽业务 | E93: 专票（6%） | F93: =ROUND(SUMIF([1]开票!$A$2:$A$1750,[1]申请!AQ93,[1]开票!$C$2:$C$1750),2) -> 36000.85 | G93: =ROUND(SUMIF([1]开票!$A$2:$A$1750,[1]申请!AQ93,[1]开票!$D$2:$D$1750),2) -> 0 | H93: =ROUND(SUMIF([1]开票!$A$2:$A$1750,[1]申请!AQ93,[1]开票!$E$2:$E$1750),2) -> 2160.05 | I93: =SUM(F93:H93) -> 38160.9 | L93: 38160.9 | AD93: =SUM(J93:AC93) -> 38160.9 | AE93: =AD93-SUM(J93:AC93) -> 0 | AF93: =AD93-I93 -> 0 | AG93: =ROUND(H93,2) -> 2160.05 | AH93: =ROUND(AG93*0.07,2) -> 151.2 | AI93: =ROUND(AG93*0.03,2) -> 64.8 | AJ93: =ROUND(AG93*0.02,2) -> 43.2 | AK93: =IF(AR93,Y93/(AR93*1.12)*AR93,0) -> 0 | AL93: =ROUND(Y93-AK93,2) -> 0 | AM93: =ROUND(AG93-AK93,2) -> 2160.05 | AN93: =ROUND(AM93*0.07,2) -> 151.2 | AO93: =ROUND(AM93*0.03,2) -> 64.8 | AP93: =ROUND(AH93+AI93+AJ93-AL93-AN93-AO93,2) -> 43.2 | AQ93: ="TJ"&A93 -> TJ202512081407000571281 | AR93: =IF(E93="无全额",0,MID(E93,4,2)*1) -> 0.06
A94: 202512081442000167995 | B94: 江西南商文旅产业发展有限公司 | C94: 劳务承揽 | D94: 承揽业务 | E94: 专票（6%） | F94: =ROUND(SUMIF([1]开票!$A$2:$A$1750,[1]申请!AQ94,[1]开票!$C$2:$C$1750),2) -> 16137.92 | G94: =ROUND(SUMIF([1]开票!$A$2:$A$1750,[1]申请!AQ94,[1]开票!$D$2:$D$1750),2) -> 0 | H94: =ROUND(SUMIF([1]开票!$A$2:$A$1750,[1]申请!AQ94,[1]开票!$E$2:$E$1750),2) -> 968.28 | I94: =SUM(F94:H94) -> 17106.2 | J94: 200 | S94: 9550.4 | T94: 505.6 | U94: 3348 | V94: 2400 | X94: 25.05 | Y94: 1077.15 | AD94: =SUM(J94:AC94) -> 17106.2 | AE94: =AD94-SUM(J94:AC94) -> 0 | AF94: =AD94-I94 -> 0 | AG94: =ROUND(H94,2) -> 968.28 | AH94: =ROUND(AG94*0.07,2) -> 67.78 | AI94: =ROUND(AG94*0.03,2) -> 29.05 | AJ94: =ROUND(AG94*0.02,2) -> 19.37 | AK94: =IF(AR94,Y94/(AR94*1.12)*AR94,0) -> 961.74107 | AL94: =ROUND(Y94-AK94,2) -> 115.41 | AM94: =ROUND(AG94-AK94,2) -> 6.54 | AN94: =ROUND(AM94*0.07,2) -> 0.46 | AO94: =ROUND(AM94*0.03,2) -> 0.2 | AP94: =ROUND(AH94+AI94+AJ94-AL94-AN94-AO94,2) -> 0.13 | AQ94: ="TJ"&A94 -> TJ202512081442000167995 | AR94: =IF(E94="无全额",0,MID(E94,4,2)*1) -> 0.06
A95: 202512081503000107781 | B95: 软通动力信息技术（集团）股份有限公司 | C95: 劳务承揽 | D95: 小时间承揽 | E95: 专票（6%） | F95: =ROUND(SUMIF([1]开票!$A$2:$A$1750,[1]申请!AQ95,[1]开票!$C$2:$C$1750),2) -> 807.55 | G95: =ROUND(SUMIF([1]开票!$A$2:$A$1750,[1]申请!AQ95,[1]开票!$D$2:$D$1750),2) -> 0 | H95: =ROUND(SUMIF([1]开票!$A$2:$A$1750,[1]申请!AQ95,[1]开票!$E$2:$E$1750),2) -> 48.45 | I95: =SUM(F95:H95) -> 856 | Q95: 56 | Z95: 800 | AD95: =SUM(J95:AC95) -> 856 | AE95: =AD95-SUM(J95:AC95) -> 0 | AF95: =AD95-I95 -> 0 | AG95: =ROUND(H95,2) -> 48.45 | AH95: =ROUND(AG95*0.07,2) -> 3.39 | AI95: =ROUND(AG95*0.03,2) -> 1.45 | AJ95: =ROUND(AG95*0.02,2) -> 0.97 | AK95: =IF(AR95,Y95/(AR95*1.12)*AR95,0) -> 0 | AL95: =ROUND(Y95-AK95,2) -> 0 | AM95: =ROUND(AG95-AK95,2) -> 48.45 | AN95: =ROUND(AM95*0.07,2) -> 3.39 | AO95: =ROUND(AM95*0.03,2) -> 1.45 | AP95: =ROUND(AH95+AI95+AJ95-AL95-AN95-AO95,2) -> 0.97 | AQ95: ="TJ"&A95 -> TJ202512081503000107781 | AR95: =IF(E95="无全额",0,MID(E95,4,2)*1) -> 0.06
A96: 202512081504000504868 | B96: 上海园林格兰云天大酒店有限公司 | C96: 劳务承揽 | D96: 承揽业务 | E96: 专票（6%） | F96: =ROUND(SUMIF([1]开票!$A$2:$A$1750,[1]申请!AQ96,[1]开票!$C$2:$C$1750),2) -> 35517.8 | G96: =ROUND(SUMIF([1]开票!$A$2:$A$1750,[1]申请!AQ96,[1]开票!$D$2:$D$1750),2) -> 0 | H96: =ROUND(SUMIF([1]开票!$A$2:$A$1750,[1]申请!AQ96,[1]开票!$E$2:$E$1750),2) -> 2131.07 | I96: =SUM(F96:H96) -> 37648.87 | L96: 37648.87 | AD96: =SUM(J96:AC96) -> 37648.87 | AE96: =AD96-SUM(J96:AC96) -> 0 | AF96: =AD96-I96 -> 0 | AG96: =ROUND(H96,2) -> 2131.07 | AH96: =ROUND(AG96*0.07,2) -> 149.17 | AI96: =ROUND(AG96*0.03,2) -> 63.93 | AJ96: =ROUND(AG96*0.02,2) -> 42.62 | AK96: =IF(AR96,Y96/(AR96*1.12)*AR96,0) -> 0 | AL96: =ROUND(Y96-AK96,2) -> 0 | AM96: =ROUND(AG96-AK96,2) -> 2131.07 | AN96: =ROUND(AM96*0.07,2) -> 149.17 | AO96: =ROUND(AM96*0.03,2) -> 63.93 | AP96: =ROUND(AH96+AI96+AJ96-AL96-AN96-AO96,2) -> 42.62 | AQ96: ="TJ"&A96 -> TJ202512081504000504868 | AR96: =IF(E96="无全额",0,MID(E96,4,2)*1) -> 0.06
A97: 202512081635000576506 | B97: 辉山乳业（沈阳）销售有限公司 | C97: 劳务承揽 | D97: 承揽业务 | E97: 专票（6%） | F97: =ROUND(SUMIF([1]开票!$A$2:$A$1750,[1]申请!AQ97,[1]开票!$C$2:$C$1750),2) -> 482042.43 | G97: =ROUND(SUMIF([1]开票!$A$2:$A$1750,[1]申请!AQ97,[1]开票!$D$2:$D$1750),2) -> 0 | H97: =ROUND(SUMIF([1]开票!$A$2:$A$1750,[1]申请!AQ97,[1]开票!$E$2:$E$1750),2) -> 28922.55 | I97: =SUM(F97:H97) -> 510964.98 | L97: 510964.98 | AD97: =SUM(J97:AC97) -> 510964.98 | AE97: =AD97-SUM(J97:AC97) -> 0 | AF97: =AD97-I97 -> 0 | AG97: =ROUND(H97,2) -> 28922.55 | AH97: =ROUND(AG97*0.07,2) -> 2024.58 | AI97: =ROUND(AG97*0.03,2) -> 867.68 | AJ97: =ROUND(AG97*0.02,2) -> 578.45 | AK97: =IF(AR97,Y97/(AR97*1.12)*AR97,0) -> 0 | AL97: =ROUND(Y97-AK97,2) -> 0 | AM97: =ROUND(AG97-AK97,2) -> 28922.55 | AN97: =ROUND(AM97*0.07,2) -> 2024.58 | AO97: =ROUND(AM97*0.03,2) -> 867.68 | AP97: =ROUND(AH97+AI97+AJ97-AL97-AN97-AO97,2) -> 578.45 | AQ97: ="TJ"&A97 -> TJ202512081635000576506 | AR97: =IF(E97="无全额",0,MID(E97,4,2)*1) -> 0.06
A98: 202512090906000485493 | B98: 范沃森（上海）自动化测试设备有限公司 | C98: 劳务派遣 | D98: 派遣业务 | E98: 专票（5%） | F98: =ROUND(SUMIF([1]开票!$A$2:$A$1750,[1]申请!AQ98,[1]开票!$C$2:$C$1750),2) -> 190.48 | G98: =ROUND(SUMIF([1]开票!$A$2:$A$1750,[1]申请!AQ98,[1]开票!$D$2:$D$1750),2) -> 47854.46 | H98: =ROUND(SUMIF([1]开票!$A$2:$A$1750,[1]申请!AQ98,[1]开票!$E$2:$E$1750),2) -> 9.52 | I98: =SUM(F98:H98) -> 48054.46 | J98: 200 | S98: 27536.4 | T98: 1281.82 | U98: 13113.68 | V98: 5922.56 | AD98: =SUM(J98:AC98) -> 48054.46 | AE98: =AD98-SUM(J98:AC98) -> 0 | AF98: =AD98-I98 -> 0 | AG98: =ROUND(H98,2) -> 9.52 | AH98: =ROUND(AG98*0.07,2) -> 0.67 | AI98: =ROUND(AG98*0.03,2) -> 0.29 | AJ98: =ROUND(AG98*0.02,2) -> 0.19 | AK98: =IF(AR98,Y98/(AR98*1.12)*AR98,0) -> 0 | AL98: =ROUND(Y98-AK98,2) -> 0 | AM98: =ROUND(AG98-AK98,2) -> 9.52 | AN98: =ROUND(AM98*0.07,2) -> 0.67 | AO98: =ROUND(AM98*0.03,2) -> 0.29 | AP98: =ROUND(AH98+AI98+AJ98-AL98-AN98-AO98,2) -> 0.19 | AQ98: ="TJ"&A98 -> TJ202512090906000485493 | AR98: =IF(E98="无全额",0,MID(E98,4,2)*1) -> 0.05
A99: 202512090927000176116 | B99: 广州花都车城建设投资开发有限公司 | C99: 劳务承揽 | D99: 承揽业务 | E99: 专票（6%） | F99: =ROUND(SUMIF([1]开票!$A$2:$A$1750,[1]申请!AQ99,[1]开票!$C$2:$C$1750),2) -> 20217.36 | G99: =ROUND(SUMIF([1]开票!$A$2:$A$1750,[1]申请!AQ99,[1]开票!$D$2:$D$1750),2) -> 0 | H99: =ROUND(SUMIF([1]开票!$A$2:$A$1750,[1]申请!AQ99,[1]开票!$E$2:$E$1750),2) -> 1213.04 | I99: =SUM(F99:H99) -> 21430.4 | L99: 21430.4 | AD99: =SUM(J99:AC99) -> 21430.4 | AE99: =AD99-SUM(J99:AC99) -> 0 | AF99: =AD99-I99 -> 0 | AG99: =ROUND(H99,2) -> 1213.04 | AH99: =ROUND(AG99*0.07,2) -> 84.91 | AI99: =ROUND(AG99*0.03,2) -> 36.39 | AJ99: =ROUND(AG99*0.02,2) -> 24.26 | AK99: =IF(AR99,Y99/(AR99*1.12)*AR99,0) -> 0 | AL99: =ROUND(Y99-AK99,2) -> 0 | AM99: =ROUND(AG99-AK99,2) -> 1213.04 | AN99: =ROUND(AM99*0.07,2) -> 84.91 | AO99: =ROUND(AM99*0.03,2) -> 36.39 | AP99: =ROUND(AH99+AI99+AJ99-AL99-AN99-AO99,2) -> 24.26 | AQ99: ="TJ"&A99 -> TJ202512090927000176116 | AR99: =IF(E99="无全额",0,MID(E99,4,2)*1) -> 0.06
A100: 202512091019000351050 | B100: 【天虹超市-华南三区 】 | C100: 劳务承揽 | D100: 承揽业务 | E100: 专票（6%） | F100: =ROUND(SUMIF([1]开票!$A$2:$A$1750,[1]申请!AQ100,[1]开票!$C$2:$C$1750),2) -> 65133.56 | G100: =ROUND(SUMIF([1]开票!$A$2:$A$1750,[1]申请!AQ100,[1]开票!$D$2:$D$1750),2) -> 0 | H100: =ROUND(SUMIF([1]开票!$A$2:$A$1750,[1]申请!AQ100,[1]开票!$E$2:$E$1750),2) -> 3908.01 | I100: =SUM(F100:H100) -> 69041.57 | L100: 69041.57 | AD100: =SUM(J100:AC100) -> 69041.57 | AE100: =AD100-SUM(J100:AC100) -> 0 | AF100: =AD100-I100 -> 0 | AG100: =ROUND(H100,2) -> 3908.01 | AH100: =ROUND(AG100*0.07,2) -> 273.56 | AI100: =ROUND(AG100*0.03,2) -> 117.24 | AJ100: =ROUND(AG100*0.02,2) -> 78.16 | AK100: =IF(AR100,Y100/(AR100*1.12)*AR100,0) -> 0 | AL100: =ROUND(Y100-AK100,2) -> 0 | AM100: =ROUND(AG100-AK100,2) -> 3908.01 | AN100: =ROUND(AM100*0.07,2) -> 273.56 | AO100: =ROUND(AM100*0.03,2) -> 117.24 | AP100: =ROUND(AH100+AI100+AJ100-AL100-AN100-AO100,2) -> 78.16 | AQ100: ="TJ"&A100 -> TJ202512091019000351050 | AR100: =IF(E100="无全额",0,MID(E100,4,2)*1) -> 0.06
...

Sheet Sheet2

Sheet Sheet3
